Workbook

Sheet business_units
A1: bu_id | B1: bu_name | C1: primary_product | D1: target_hedge_ratio | E1: hedging_policy | F1: sanctioned_credit_line_inr
A2: BU01 | B2: Packaging Films | C2: Flexible packaging films | D2: 0.7 | E2: Hedge 60-80% of USD/EUR exports and crude-linked feedstock | F2: 1365200000
A3: BU02 | B3: Industrial Resins | C3: Commodity and industrial resins | D3: 0.2 | E3: Hedge 20% of crude-linked feedstock; exports left open | F3: 415500000
A4: BU03 | B4: Specialty Chemicals | C4: Specialty chemicals for export | D4: 0.5 | E4: Hedge about 50% of EUR/USD exports | F4: 490600000
A5: BU04 | B5: Consumer Plastics | C5: Domestic consumer plastics | D5: 0.5 | E5: Hedge about 50% of feedstock; mainly INR sales | F5: 617700000
A6: BU05 | B6: Engineering Compounds | C6: Engineering plastic compounds | D6: 0.35 | E6: Hedge 30-40% of feedstock and exports | F6: 423500000

Sheet treasury_monthly
A1: treasury_id | B1: bu_id | C1: month_end | D1: opening_cash | E1: cash_inflows | F1: cash_outflows | G1: net_borrowing | H1: inventory | I1: trade_receivables | J1: current_assets | K1: current_liabilities | L1: short_term_debt_due_30d | M1: undrawn_credit_line | N1: closing_cash
A2: TR0001 | B2: BU01 | C2: 45046 | D2: 182032291 | E2: 238643650 | F2: 170652359 | G2: -36066175 | H2: 84227738 | I2: 378518564 | J2: 676703709 | K2: 445917720 | L2: 288734020 | M2: 1279953499 | N2: 213957407
A3: TR0002 | B3: BU01 | C3: 45077 | D3: 213957407 | E3: 185489721 | F3: 161087598 | G3: 0 | H3: 231339937 | I3: 491629258 | J3: 961328725 | K3: 514388812 | L3: 288760805 | M3: 1279953499 | N3: 238359530
A4: TR0003 | B4: BU01 | C4: 45107 | D4: 238359530 | E4: 200846909 | F4: 284933671 | G4: 0 | H4: 215563578 | I4: 634911689 | J4: 1004748035 | K4: 434572250 | L4: 283318475 | M4: 1279953499 | N4: 154272768
A5: TR0004 | B5: BU01 | C5: 45138 | D5: 154272767 | E5: 360628017 | F5: 204497681 | G5: -58501607 | H5: 205132507 | I5: 542033922 | J5: 999067925 | K5: 466334652 | L5: 268045049 | M5: 1338455106 | N5: 251901496
A6: TR0005 | B6: BU01 | C6: 45169 | D6: 251901496 | E6: 274644386 | F6: 270867867 | G6: -26787079 | H6: 188177282 | I6: 538222910 | J6: 955291127 | K6: 443487246 | L6: 262533701 | M6: 1365242185 | N6: 228890936
A7: TR0006 | B7: BU01 | C7: 45199 | D7: 228890935 | E7: 271117290 | F7: 294679437 | G7: 0 | H7: 247800017 | I7: 664459943 | J7: 1117588747 | K7: 443487246 | L7: 270586020 | M7: 1365242185 | N7: 205328788
A8: TR0007 | B8: BU01 | C8: 45230 | D8: 205328788 | E8: 246902321 | F8: 269308254 | G8: 0 | H8: 335048380 | I8: 836023271 | J8: 1353994507 | K8: 528666336 | L8: 278172810 | M8: 1365242185 | N8: 182922855
A9: TR0008 | B9: BU01 | C9: 45260 | D9: 182922856 | E9: 462805637 | F9: 324941577 | G9: 0 | H9: 316793730 | I9: 815137342 | J9: 1452717989 | K9: 498479231 | L9: 251706801 | M9: 1365242185 | N9: 320786916
A10: TR0009 | B10: BU01 | C10: 45291 | D10: 320786916 | E10: 455156070 | F10: 346519095 | G10: 0 | H10: 312042736 | I10: 830479857 | J10: 1571946484 | K10: 515698065 | L10: 265310450 | M10: 1365242185 | N10: 429423891
A11: TR0010 | B11: BU01 | C11: 45322 | D11: 429423891 | E11: 240600243 | F11: 327635934 | G11: 0 | H11: 309616686 | I11: 835631745 | J11: 1487636632 | K11: 515698065 | L11: 308850927 | M11: 1365242185 | N11: 342388200
A12: TR0011 | B12: BU01 | C12: 45351 | D12: 342388200 | E12: 331910708 | F12: 336108391 | G12: 0 | H12: 304121503 | I12: 1049972322 | J12: 1692284343 | K12: 481283712 | L12: 270939498 | M12: 1365242185 | N12: 338190517
A13: TR0012 | B13: BU01 | C13: 45382 | D13: 338190517 | E13: 344175936 | F13: 383157775 | G13: 0 | H13: 282207782 | I13: 1215148322 | J13: 1796564782 | K13: 629308980 | L13: 395728390 | M13: 1365242185 | N13: 299208678
... A120: TR0120 | B120: BU05 | C120: 45747 | D120: 217377521 | E120: 129668482 | F120: 142420879 | G120: 0 | H120: 168193379 | I120: 382008188 | J120: 754826690 | K120: 212376416 | L120: 97090778 | M120: 423452545 | N120: 204625124

Sheet invoices
A1: invoice_id | B1: customer_id | C1: bu_id | D1: invoice_date | E1: due_date | F1: currency | G1: invoice_amount | H1: paid_date | I1: status | J1: hedged_flag | K1: hedge_rate | L1: amount_paid | M1: fx_rate_inv | N1: invoice_amount_inr | O1: open_balance_inr | P1: days_overdue | Q1: days_late | R1: aging
A2: INV002586 | B2: C0019 | C2: BU05 | D2: 45721 | E2: 45811 | F2: EUR | G2: 497215.46 | I2: OPEN | J2: N | L2: 0 | M2: =IF(F2="INR",1,INDEX('rates'!$B$2:$C$522,MATCH(D2,'rates'!$A$2:$A$522,1),MATCH(F2&"/INR",'rates'!$B$1:$C$1,0))) -> 93.6278 | N2: =G2*M2 -> 46553190 | O2: =IF(OR(I2="OPEN",I2="PARTIALLY PAID"),(G2-L2)*M2,0) -> 46553190 | P2: =IF(O2>0,MAX(0,DATE(2025,3,31)-E2),0) -> 0 | Q2: =IF(H2="","",H2-E2) | R2: =IF(O2=0,"Not open",IF(P2=0,"Not yet due",IF(P2<=30,"1-30",IF(P2<=60,"31-60",IF(P2<=90,"61-90","90+"))))) -> Not yet due
A3: INV002659 | B3: C0049 | C3: BU01 | D3: 45738 | E3: 45768 | F3: INR | G3: 44151066 | I3: OPEN | J3: N | L3: 0 | M3: =IF(F3="INR",1,INDEX('rates'!$B$2:$C$522,MATCH(D3,'rates'!$A$2:$A$522,1),MATCH(F3&"/INR",'rates'!$B$1:$C$1,0))) -> 1 | N3: =G3*M3 -> 44151066 | O3: =IF(OR(I3="OPEN",I3="PARTIALLY PAID"),(G3-L3)*M3,0) -> 44151066 | P3: =IF(O3>0,MAX(0,DATE(2025,3,31)-E3),0) -> 0 | Q3: =IF(H3="","",H3-E3) | R3: =IF(O3=0,"Not open",IF(P3=0,"Not yet due",IF(P3<=30,"1-30",IF(P3<=60,"31-60",IF(P3<=90,"61-90","90+"))))) -> Not yet due
A4: INV002380 | B4: C0161 | C4: BU03 | D4: 45667 | E4: 45757 | F4: USD | G4: 431946.95 | I4: OPEN | J4: N | L4: 0 | M4: =IF(F4="INR",1,INDEX('rates'!$B$2:$C$522,MATCH(D4,'rates'!$A$2:$A$522,1),MATCH(F4&"/INR",'rates'!$B$1:$C$1,0))) -> 85.96 | N4: =G4*M4 -> 37130160 | O4: =IF(OR(I4="OPEN",I4="PARTIALLY PAID"),(G4-L4)*M4,0) -> 37130160 | P4: =IF(O4>0,MAX(0,DATE(2025,3,31)-E4),0) -> 0 | Q4: =IF(H4="","",H4-E4) | R4: =IF(O4=0,"Not open",IF(P4=0,"Not yet due",IF(P4<=30,"1-30",IF(P4<=60,"31-60",IF(P4<=90,"61-90","90+"))))) -> Not yet due
A5: INV002609 | B5: C0039 | C5: BU04 | D5: 45727 | E5: 45787 | F5: INR | G5: 36730540 | I5: OPEN | J5: N | L5: 0 | M5: =IF(F5="INR",1,INDEX('rates'!$B$2:$C$522,MATCH(D5,'rates'!$A$2:$A$522,1),MATCH(F5&"/INR",'rates'!$B$1:$C$1,0))) -> 1 | N5: =G5*M5 -> 36730540 | O5: =IF(OR(I5="OPEN",I5="PARTIALLY PAID"),(G5-L5)*M5,0) -> 36730540 | P5: =IF(O5>0,MAX(0,DATE(2025,3,31)-E5),0) -> 0 | Q5: =IF(H5="","",H5-E5) | R5: =IF(O5=0,"Not open",IF(P5=0,"Not yet due",IF(P5<=30,"1-30",IF(P5<=60,"31-60",IF(P5<=90,"61-90","90+"))))) -> Not yet due
A6: INV002371 | B6: C0111 | C6: BU01 | D6: 45666 | E6: 45756 | F6: EUR | G6: 358641.79 | I6: OPEN | J6: Y | K6: 88.6942 | L6: 0 | M6: =IF(F6="INR",1,INDEX('rates'!$B$2:$C$522,MATCH(D6,'rates'!$A$2:$A$522,1),MATCH(F6&"/INR",'rates'!$B$1:$C$1,0))) -> 88.4289 | N6: =G6*M6 -> 31714299 | O6: =IF(OR(I6="OPEN",I6="PARTIALLY PAID"),(G6-L6)*M6,0) -> 31714299 | P6: =IF(O6>0,MAX(0,DATE(2025,3,31)-E6),0) -> 0 | Q6: =IF(H6="","",H6-E6) | R6: =IF(O6=0,"Not open",IF(P6=0,"Not yet due",IF(P6<=30,"1-30",IF(P6<=60,"31-60",IF(P6<=90,"61-90","90+"))))) -> Not yet due
A7: INV002617 | B7: C0138 | C7: BU03 | D7: 45728 | E7: 45758 | F7: INR | G7: 30751759 | I7: OPEN | J7: N | L7: 0 | M7: =IF(F7="INR",1,INDEX('rates'!$B$2:$C$522,MATCH(D7,'rates'!$A$2:$A$522,1),MATCH(F7&"/INR",'rates'!$B$1:$C$1,0))) -> 1 | N7: =G7*M7 -> 30751759 | O7: =IF(OR(I7="OPEN",I7="PARTIALLY PAID"),(G7-L7)*M7,0) -> 30751759 | P7: =IF(O7>0,MAX(0,DATE(2025,3,31)-E7),0) -> 0 | Q7: =IF(H7="","",H7-E7) | R7: =IF(O7=0,"Not open",IF(P7=0,"Not yet due",IF(P7<=30,"1-30",IF(P7<=60,"31-60",IF(P7<=90,"61-90","90+"))))) -> Not yet due
A8: INV002511 | B8: C0166 | C8: BU05 | D8: 45701 | E8: 45791 | F8: INR | G8: 29692974 | I8: OPEN | J8: N | L8: 0 | M8: =IF(F8="INR",1,INDEX('rates'!$B$2:$C$522,MATCH(D8,'rates'!$A$2:$A$522,1),MATCH(F8&"/INR",'rates'!$B$1:$C$1,0))) -> 1 | N8: =G8*M8 -> 29692974 | O8: =IF(OR(I8="OPEN",I8="PARTIALLY PAID"),(G8-L8)*M8,0) -> 29692974 | P8: =IF(O8>0,MAX(0,DATE(2025,3,31)-E8),0) -> 0 | Q8: =IF(H8="","",H8-E8) | R8: =IF(O8=0,"Not open",IF(P8=0,"Not yet due",IF(P8<=30,"1-30",IF(P8<=60,"31-60",IF(P8<=90,"61-90","90+"))))) -> Not yet due
A9: INV002628 | B9: C0029 | C9: BU02 | D9: 45731 | E9: 45821 | F9: INR | G9: 28920720 | I9: OPEN | J9: N | L9: 0 | M9: =IF(F9="INR",1,INDEX('rates'!$B$2:$C$522,MATCH(D9,'rates'!$A$2:$A$522,1),MATCH(F9&"/INR",'rates'!$B$1:$C$1,0))) -> 1 | N9: =G9*M9 -> 28920720 | O9: =IF(OR(I9="OPEN",I9="PARTIALLY PAID"),(G9-L9)*M9,0) -> 28920720 | P9: =IF(O9>0,MAX(0,DATE(2025,3,31)-E9),0) -> 0 | Q9: =IF(H9="","",H9-E9) | R9: =IF(O9=0,"Not open",IF(P9=0,"Not yet due",IF(P9<=30,"1-30",IF(P9<=60,"31-60",IF(P9<=90,"61-90","90+"))))) -> Not yet due
A10: INV002585 | B10: C0211 | C10: BU01 | D10: 45720 | E10: 45765 | F10: INR | G10: 27466762 | I10: OPEN | J10: N | L10: 0 | M10: =IF(F10="INR",1,INDEX('rates'!$B$2:$C$522,MATCH(D10,'rates'!$A$2:$A$522,1),MATCH(F10&"/INR",'rates'!$B$1:$C$1,0))) -> 1 | N10: =G10*M10 -> 27466762 | O10: =IF(OR(I10="OPEN",I10="PARTIALLY PAID"),(G10-L10)*M10,0) -> 27466762 | P10: =IF(O10>0,MAX(0,DATE(2025,3,31)-E10),0) -> 0 | Q10: =IF(H10="","",H10-E10) | R10: =IF(O10=0,"Not open",IF(P10=0,"Not yet due",IF(P10<=30,"1-30",IF(P10<=60,"31-60",IF(P10<=90,"61-90","90+"))))) -> Not yet due
A11: INV002557 | B11: C0224 | C11: BU02 | D11: 45710 | E11: 45740 | F11: EUR | G11: 291923.04 | I11: OPEN | J11: N | L11: 0 | M11: =IF(F11="INR",1,INDEX('rates'!$B$2:$C$522,MATCH(D11,'rates'!$A$2:$A$522,1),MATCH(F11&"/INR",'rates'!$B$1:$C$1,0))) -> 90.6448 | N11: =G11*M11 -> 26461306 | O11: =IF(OR(I11="OPEN",I11="PARTIALLY PAID"),(G11-L11)*M11,0) -> 26461306 | P11: =IF(O11>0,MAX(0,DATE(2025,3,31)-E11),0) -> 7 | Q11: =IF(H11="","",H11-E11) | R11: =IF(O11=0,"Not open",IF(P11=0,"Not yet due",IF(P11<=30,"1-30",IF(P11<=60,"31-60",IF(P11<=90,"61-90","90+"))))) -> 1-30
A12: INV002572 | B12: C0146 | C12: BU01 | D12: 45717 | E12: 45777 | F12: USD | G12: 289490.53 | I12: OPEN | J12: Y | K12: 87.7917 | L12: 0 | M12: =IF(F12="INR",1,INDEX('rates'!$B$2:$C$522,MATCH(D12,'rates'!$A$2:$A$522,1),MATCH(F12&"/INR",'rates'!$B$1:$C$1,0))) -> 87.5 | N12: =G12*M12 -> 25330421 | O12: =IF(OR(I12="OPEN",I12="PARTIALLY PAID"),(G12-L12)*M12,0) -> 25330421 | P12: =IF(O12>0,MAX(0,DATE(2025,3,31)-E12),0) -> 0 | Q12: =IF(H12="","",H12-E12) | R12: =IF(O12=0,"Not open",IF(P12=0,"Not yet due",IF(P12<=30,"1-30",IF(P12<=60,"31-60",IF(P12<=90,"61-90","90+"))))) -> Not yet due
A13: INV002336 | B13: C0153 | C13: BU03 | D13: 45658 | E13: 45748 | F13: INR | G13: 24438240 | I13: OPEN | J13: N | L13: 0 | M13: =IF(F13="INR",1,INDEX('rates'!$B$2:$C$522,MATCH(D13,'rates'!$A$2:$A$522,1),MATCH(F13&"/INR",'rates'!$B$1:$C$1,0))) -> 1 | N13: =G13*M13 -> 24438240 | O13: =IF(OR(I13="OPEN",I13="PARTIALLY PAID"),(G13-L13)*M13,0) -> 24438240 | P13: =IF(O13>0,MAX(0,DATE(2025,3,31)-E13),0) -> 0 | Q13: =IF(H13="","",H13-E13) | R13: =IF(O13=0,"Not open",IF(P13=0,"Not yet due",IF(P13<=30,"1-30",IF(P13<=60,"31-60",IF(P13<=90,"61-90","90+"))))) -> Not yet due
A14: INV002644 | B14: C0005 | C14: BU05 | D14: 45734 | E14: 45764 | F14: INR | G14: 24397292 | I14: OPEN | J14: N | L14: 0 | M14: =IF(F14="INR",1,INDEX('rates'!$B$2:$C$522,MATCH(D14,'rates'!$A$2:$A$522,1),MATCH(F14&"/INR",'rates'!$B$1:$C$1,0))) -> 1 | N14: =G14*M14 -> 24397292 | O14: =IF(OR(I14="OPEN",I14="PARTIALLY PAID"),(G14-L14)*M14,0) -> 24397292 | P14: =IF(O14>0,MAX(0,DATE(2025,3,31)-E14),0) -> 0 | Q14: =IF(H14="","",H14-E14) | R14: =IF(O14=0,"Not open",IF(P14=0,"Not yet due",IF(P14<=30,"1-30",IF(P14<=60,"31-60",IF(P14<=90,"61-90","90+"))))) -> Not yet due
A15: INV002365 | B15: C0212 | C15: BU05 | D15: 45665 | E15: 45755 | F15: INR | G15: 24031583 | I15: OPEN | J15: N | L15: 0 | M15: =IF(F15="INR",1,INDEX('rates'!$B$2:$C$522,MATCH(D15,'rates'!$A$2:$A$522,1),MATCH(F15&"/INR",'rates'!$B$1:$C$1,0))) -> 1 | N15: =G15*M15 -> 24031583 | O15: =IF(OR(I15="OPEN",I15="PARTIALLY PAID"),(G15-L15)*M15,0) -> 24031583 | P15: =IF(O15>0,MAX(0,DATE(2025,3,31)-E15),0) -> 0 | Q15: =IF(H15="","",H15-E15) | R15: =IF(O15=0,"Not open",IF(P15=0,"Not yet due",IF(P15<=30,"1-30",IF(P15<=60,"31-60",IF(P15<=90,"61-90","90+"))))) -> Not yet due
A16: INV002627 | B16: C0236 | C16: BU01 | D16: 45730 | E16: 45790 | F16: EUR | G16: 250227.09 | I16: OPEN | J16: Y | K16: 94.7756 | L16: 0 | M16: =IF(F16="INR",1,INDEX('rates'!$B$2:$C$522,MATCH(D16,'rates'!$A$2:$A$522,1),MATCH(F16&"/INR",'rates'!$B$1:$C$1,0))) -> 94.5864 | N16: =G16*M16 -> 23668080 | O16: =IF(OR(I16="OPEN",I16="PARTIALLY PAID"),(G16-L16)*M16,0) -> 23668080 | P16: =IF(O16>0,MAX(0,DATE(2025,3,31)-E16),0) -> 0 | Q16: =IF(H16="","",H16-E16) | R16: =IF(O16=0,"Not open",IF(P16=0,"Not yet due",IF(P16<=30,"1-30",IF(P16<=60,"31-60",IF(P16<=90,"61-90","90+"))))) -> Not yet due
A17: INV002509 | B17: C0141 | C17: BU01 | D17: 45701 | E17: 45761 | F17: INR | G17: 23523276 | I17: OPEN | J17: N | L17: 0 | M17: =IF(F17="INR",1,INDEX('rates'!$B$2:$C$522,MATCH(D17,'rates'!$A$2:$A$522,1),MATCH(F17&"/INR",'rates'!$B$1:$C$1,0))) -> 1 | N17: =G17*M17 -> 23523276 | O17: =IF(OR(I17="OPEN",I17="PARTIALLY PAID"),(G17-L17)*M17,0) -> 23523276 | P17: =IF(O17>0,MAX(0,DATE(2025,3,31)-E17),0) -> 0 | Q17: =IF(H17="","",H17-E17) | R17: =IF(O17=0,"Not open",IF(P17=0,"Not yet due",IF(P17<=30,"1-30",IF(P17<=60,"31-60",IF(P17<=90,"61-90","90+"))))) -> Not yet due
A18: INV002615 | B18: C0198 | C18: BU01 | D18: 45727 | E18: 45772 | F18: USD | G18: 266232.61 | I18: OPEN | J18: Y | K18: 87.3779 | L18: 0 | M18: =IF(F18="INR",1,INDEX('rates'!$B$2:$C$522,MATCH(D18,'rates'!$A$2:$A$522,1),MATCH(F18&"/INR",'rates'!$B$1:$C$1,0))) -> 87.16 | N18: =G18*M18 -> 23204834 | O18: =IF(OR(I18="OPEN",I18="PARTIALLY PAID"),(G18-L18)*M18,0) -> 23204834 | P18: =IF(O18>0,MAX(0,DATE(2025,3,31)-E18),0) -> 0 | Q18: =IF(H18="","",H18-E18) | R18: =IF(O18=0,"Not open",IF(P18=0,"Not yet due",IF(P18<=30,"1-30",IF(P18<=60,"31-60",IF(P18<=90,"61-90","90+"))))) -> Not yet due
A19: INV002447 | B19: C0198 | C19: BU01 | D19: 45684 | E19: 45729 | F19: USD | G19: 262232.01 | I19: OPEN | J19: Y | K19: 86.5558 | L19: 0 | M19: =IF(F19="INR",1,INDEX('rates'!$B$2:$C$522,MATCH(D19,'rates'!$A$2:$A$522,1),MATCH(F19&"/INR",'rates'!$B$1:$C$1,0))) -> 86.34 | N19: =G19*M19 -> 22641112 | O19: =IF(OR(I19="OPEN",I19="PARTIALLY PAID"),(G19-L19)*M19,0) -> 22641112 | P19: =IF(O19>0,MAX(0,DATE(2025,3,31)-E19),0) -> 18 | Q19: =IF(H19="","",H19-E19) | R19: =IF(O19=0,"Not open",IF(P19=0,"Not yet due",IF(P19<=30,"1-30",IF(P19<=60,"31-60",IF(P19<=90,"61-90","90+"))))) -> 1-30
A20: INV002355 | B20: C0236 | C20: BU02 | D20: 45661 | E20: 45721 | F20: EUR | G20: 242682.17 | I20: OPEN | J20: N | L20: 0 | M20: =IF(F20="INR",1,INDEX('rates'!$B$2:$C$522,MATCH(D20,'rates'!$A$2:$A$522,1),MATCH(F20&"/INR",'rates'!$B$1:$C$1,0))) -> 88.2539 | N20: =G20*M20 -> 21417648 | O20: =IF(OR(I20="OPEN",I20="PARTIALLY PAID"),(G20-L20)*M20,0) -> 21417648 | P20: =IF(O20>0,MAX(0,DATE(2025,3,31)-E20),0) -> 26 | Q20: =IF(H20="","",H20-E20) | R20: =IF(O20=0,"Not open",IF(P20=0,"Not yet due",IF(P20<=30,"1-30",IF(P20<=60,"31-60",IF(P20<=90,"61-90","90+"))))) -> 1-30
A21: INV002346 | B21: C0236 | C21: BU01 | D21: 45659 | E21: 45719 | F21: EUR | G21: 236219.66 | I21: OPEN | J21: Y | K21: 88.1641 | L21: 0 | M21: =IF(F21="INR",1,INDEX('rates'!$B$2:$C$522,MATCH(D21,'rates'!$A$2:$A$522,1),MATCH(F21&"/INR",'rates'!$B$1:$C$1,0))) -> 87.9881 | N21: =G21*M21 -> 20784519 | O21: =IF(OR(I21="OPEN",I21="PARTIALLY PAID"),(G21-L21)*M21,0) -> 20784519 | P21: =IF(O21>0,MAX(0,DATE(2025,3,31)-E21),0) -> 28 | Q21: =IF(H21="","",H21-E21) | R21: =IF(O21=0,"Not open",IF(P21=0,"Not yet due",IF(P21<=30,"1-30",IF(P21<=60,"31-60",IF(P21<=90,"61-90","90+"))))) -> 1-30
A22: INV002601 | B22: C0060 | C22: BU02 | D22: 45724 | E22: 45769 | F22: INR | G22: 20457785 | I22: OPEN | J22: N | L22: 0 | M22: =IF(F22="INR",1,INDEX('rates'!$B$2:$C$522,MATCH(D22,'rates'!$A$2:$A$522,1),MATCH(F22&"/INR",'rates'!$B$1:$C$1,0))) -> 1 | N22: =G22*M22 -> 20457785 | O22: =IF(OR(I22="OPEN",I22="PARTIALLY PAID"),(G22-L22)*M22,0) -> 20457785 | P22: =IF(O22>0,MAX(0,DATE(2025,3,31)-E22),0) -> 0 | Q22: =IF(H22="","",H22-E22) | R22: =IF(O22=0,"Not open",IF(P22=0,"Not yet due",IF(P22<=30,"1-30",IF(P22<=60,"31-60",IF(P22<=90,"61-90","90+"))))) -> Not yet due
A23: INV002555 | B23: C0111 | C23: BU01 | D23: 45710 | E23: 45800 | F23: EUR | G23: 218730.33 | I23: OPEN | J23: Y | K23: 90.9167 | L23: 0 | M23: =IF(F23="INR",1,INDEX('rates'!$B$2:$C$522,MATCH(D23,'rates'!$A$2:$A$522,1),MATCH(F23&"/INR",'rates'!$B$1:$C$1,0))) -> 90.6448 | N23: =G23*M23 -> 19826767 | O23: =IF(OR(I23="OPEN",I23="PARTIALLY PAID"),(G23-L23)*M23,0) -> 19826767 | P23: =IF(O23>0,MAX(0,DATE(2025,3,31)-E23),0) -> 0 | Q23: =IF(H23="","",H23-E23) | R23: =IF(O23=0,"Not open",IF(P23=0,"Not yet due",IF(P23<=30,"1-30",IF(P23<=60,"31-60",IF(P23<=90,"61-90","90+"))))) -> Not yet due
A24: INV001815 | B24: C0140 | C24: BU03 | D24: 45528 | E24: 45573 | F24: INR | G24: 19790384 | I24: OPEN | J24: N | L24: 0 | M24: =IF(F24="INR",1,INDEX('rates'!$B$2:$C$522,MATCH(D24,'rates'!$A$2:$A$522,1),MATCH(F24&"/INR",'rates'!$B$1:$C$1,0))) -> 1 | N24: =G24*M24 -> 19790384 | O24: =IF(OR(I24="OPEN",I24="PARTIALLY PAID"),(G24-L24)*M24,0) -> 19790384 | P24: =IF(O24>0,MAX(0,DATE(2025,3,31)-E24),0) -> 174 | Q24: =IF(H24="","",H24-E24) | R24: =IF(O24=0,"Not open",IF(P24=0,"Not yet due",IF(P24<=30,"1-30",IF(P24<=60,"31-60",IF(P24<=90,"61-90","90+"))))) -> 90+
A25: INV002403 | B25: C0166 | C25: BU03 | D25: 45672 | E25: 45762 | F25: INR | G25: 19644052 | I25: OPEN | J25: N | L25: 0 | M25: =IF(F25="INR",1,INDEX('rates'!$B$2:$C$522,MATCH(D25,'rates'!$A$2:$A$522,1),MATCH(F25&"/INR",'rates'!$B$1:$C$1,0))) -> 1 | N25: =G25*M25 -> 19644052 | O25: =IF(OR(I25="OPEN",I25="PARTIALLY PAID"),(G25-L25)*M25,0) -> 19644052 | P25: =IF(O25>0,MAX(0,DATE(2025,3,31)-E25),0) -> 0 | Q25: =IF(H25="","",H25-E25) | R25: =IF(O25=0,"Not open",IF(P25=0,"Not yet due",IF(P25<=30,"1-30",IF(P25<=60,"31-60",IF(P25<=90,"61-90","90+"))))) -> Not yet due
A26: INV001991 | B26: C0180 | C26: BU02 | D26: 45572 | E26: 45617 | F26: USD | G26: 233241.23 | I26: OPEN | J26: N | L26: 0 | M26: =IF(F26="INR",1,INDEX('rates'!$B$2:$C$522,MATCH(D26,'rates'!$A$2:$A$522,1),MATCH(F26&"/INR",'rates'!$B$1:$C$1,0))) -> 83.96 | N26: =G26*M26 -> 19582934 | O26: =IF(OR(I26="OPEN",I26="PARTIALLY PAID"),(G26-L26)*M26,0) -> 19582934 | P26: =IF(O26>0,MAX(0,DATE(2025,3,31)-E26),0) -> 130 | Q26: =IF(H26="","",H26-E26) | R26: =IF(O26=0,"Not open",IF(P26=0,"Not yet due",IF(P26<=30,"1-30",IF(P26<=60,"31-60",IF(P26<=90,"61-90","90+"))))) -> 90+
A27: INV002669 | B27: C0029 | C27: BU02 | D27: 45740 | E27: 45830 | F27: INR | G27: 19264703 | I27: OPEN | J27: N | L27: 0 | M27: =IF(F27="INR",1,INDEX('rates'!$B$2:$C$522,MATCH(D27,'rates'!$A$2:$A$522,1),MATCH(F27&"/INR",'rates'!$B$1:$C$1,0))) -> 1 | N27: =G27*M27 -> 19264703 | O27: =IF(OR(I27="OPEN",I27="PARTIALLY PAID"),(G27-L27)*M27,0) -> 19264703 | P27: =IF(O27>0,MAX(0,DATE(2025,3,31)-E27),0) -> 0 | Q27: =IF(H27="","",H27-E27) | R27: =IF(O27=0,"Not open",IF(P27=0,"Not yet due",IF(P27<=30,"1-30",IF(P27<=60,"31-60",IF(P27<=90,"61-90","90+"))))) -> Not yet due
A28: INV002544 | B28: C0228 | C28: BU04 | D28: 45707 | E28: 45752 | F28: INR | G28: 19154675 | I28: OPEN | J28: N | L28: 0 | M28: =IF(F28="INR",1,INDEX('rates'!$B$2:$C$522,MATCH(D28,'rates'!$A$2:$A$522,1),MATCH(F28&"/INR",'rates'!$B$1:$C$1,0))) -> 1 | N28: =G28*M28 -> 19154675 | O28: =IF(OR(I28="OPEN",I28="PARTIALLY PAID"),(G28-L28)*M28,0) -> 19154675 | P28: =IF(O28>0,MAX(0,DATE(2025,3,31)-E28),0) -> 0 | Q28: =IF(H28="","",H28-E28) | R28: =IF(O28=0,"Not open",IF(P28=0,"Not yet due",IF(P28<=30,"1-30",IF(P28<=60,"31-60",IF(P28<=90,"61-90","90+"))))) -> Not yet due
A29: INV002265 | B29: C0198 | C29: BU01 | D29: 45638 | E29: 45683 | F29: USD | G29: 225595.07 | I29: OPEN | J29: Y | K29: 85.0521 | L29: 0 | M29: =IF(F29="INR",1,INDEX('rates'!$B$2:$C$522,MATCH(D29,'rates'!$A$2:$A$522,1),MATCH(F29&"/INR",'rates'!$B$1:$C$1,0))) -> 84.84 | N29: =G29*M29 -> 19139486 | O29: =IF(OR(I29="OPEN",I29="PARTIALLY PAID"),(G29-L29)*M29,0) -> 19139486 | P29: =IF(O29>0,MAX(0,DATE(2025,3,31)-E29),0) -> 64 | Q29: =IF(H29="","",H29-E29) | R29: =IF(O29=0,"Not open",IF(P29=0,"Not yet due",IF(P29<=30,"1-30",IF(P29<=60,"31-60",IF(P29<=90,"61-90","90+"))))) -> 61-90
A30: INV002474 | B30: C0071 | C30: BU02 | D30: 45693 | E30: 45753 | F30: USD | G30: 217524.13 | I30: OPEN | J30: N | L30: 0 | M30: =IF(F30="INR",1,INDEX('rates'!$B$2:$C$522,MATCH(D30,'rates'!$A$2:$A$522,1),MATCH(F30&"/INR",'rates'!$B$1:$C$1,0))) -> 87.08 | N30: =G30*M30 -> 18942001 | O30: =IF(OR(I30="OPEN",I30="PARTIALLY PAID"),(G30-L30)*M30,0) -> 18942001 | P30: =IF(O30>0,MAX(0,DATE(2025,3,31)-E30),0) -> 0 | Q30: =IF(H30="","",H30-E30) | R30: =IF(O30=0,"Not open",IF(P30=0,"Not yet due",IF(P30<=30,"1-30",IF(P30<=60,"31-60",IF(P30<=90,"61-90","90+"))))) -> Not yet due
A31: INV002658 | B31: C0049 | C31: BU01 | D31: 45738 | E31: 45768 | F31: INR | G31: 18886440 | I31: OPEN | J31: N | L31: 0 | M31: =IF(F31="INR",1,INDEX('rates'!$B$2:$C$522,MATCH(D31,'rates'!$A$2:$A$522,1),MATCH(F31&"/INR",'rates'!$B$1:$C$1,0))) -> 1 | N31: =G31*M31 -> 18886440 | O31: =IF(OR(I31="OPEN",I31="PARTIALLY PAID"),(G31-L31)*M31,0) -> 18886440 | P31: =IF(O31>0,MAX(0,DATE(2025,3,31)-E31),0) -> 0 | Q31: =IF(H31="","",H31-E31) | R31: =IF(O31=0,"Not open",IF(P31=0,"Not yet due",IF(P31<=30,"1-30",IF(P31<=60,"31-60",IF(P31<=90,"61-90","90+"))))) -> Not yet due
A32: INV002531 | B32: C0238 | C32: BU05 | D32: 45703 | E32: 45763 | F32: INR | G32: 18690785 | I32: OPEN | J32: N | L32: 0 | M32: =IF(F32="INR",1,INDEX('rates'!$B$2:$C$522,MATCH(D32,'rates'!$A$2:$A$522,1),MATCH(F32&"/INR",'rates'!$B$1:$C$1,0))) -> 1 | N32: =G32*M32 -> 18690785 | O32: =IF(OR(I32="OPEN",I32="PARTIALLY PAID"),(G32-L32)*M32,0) -> 18690785 | P32: =IF(O32>0,MAX(0,DATE(2025,3,31)-E32),0) -> 0 | Q32: =IF(H32="","",H32-E32) | R32: =IF(O32=0,"Not open",IF(P32=0,"Not yet due",IF(P32<=30,"1-30",IF(P32<=60,"31-60",IF(P32<=90,"61-90","90+"))))) -> Not yet due
A33: INV002419 | B33: C0056 | C33: BU02 | D33: 45678 | E33: 45738 | F33: INR | G33: 18481351 | I33: OPEN | J33: N | L33: 0 | M33: =IF(F33="INR",1,INDEX('rates'!$B$2:$C$522,MATCH(D33,'rates'!$A$2:$A$522,1),MATCH(F33&"/INR",'rates'!$B$1:$C$1,0))) -> 1 | N33: =G33*M33 -> 18481351 | O33: =IF(OR(I33="OPEN",I33="PARTIALLY PAID"),(G33-L33)*M33,0) -> 18481351 | P33: =IF(O33>0,MAX(0,DATE(2025,3,31)-E33),0) -> 9 | Q33: =IF(H33="","",H33-E33) | R33: =IF(O33=0,"Not open",IF(P33=0,"Not yet due",IF(P33<=30,"1-30",IF(P33<=60,"31-60",IF(P33<=90,"61-90","90+"))))) -> 1-30
A34: INV002482 | B34: C0103 | C34: BU04 | D34: 45694 | E34: 45754 | F34: INR | G34: 18249855 | I34: OPEN | J34: N | L34: 0 | M34: =IF(F34="INR",1,INDEX('rates'!$B$2:$C$522,MATCH(D34,'rates'!$A$2:$A$522,1),MATCH(F34&"/INR",'rates'!$B$1:$C$1,0))) -> 1 | N34: =G34*M34 -> 18249855 | O34: =IF(OR(I34="OPEN",I34="PARTIALLY PAID"),(G34-L34)*M34,0) -> 18249855 | P34: =IF(O34>0,MAX(0,DATE(2025,3,31)-E34),0) -> 0 | Q34: =IF(H34="","",H34-E34) | R34: =IF(O34=0,"Not open",IF(P34=0,"Not yet due",IF(P34<=30,"1-30",IF(P34<=60,"31-60",IF(P34<=90,"61-90","90+"))))) -> Not yet due
A35: INV002663 | B35: C0138 | C35: BU03 | D35: 45738 | E35: 45768 | F35: INR | G35: 18108442 | I35: OPEN | J35: N | L35: 0 | M35: =IF(F35="INR",1,INDEX('rates'!$B$2:$C$522,MATCH(D35,'rates'!$A$2:$A$522,1),MATCH(F35&"/INR",'rates'!$B$1:$C$1,0))) -> 1 | N35: =G35*M35 -> 18108442 | O35: =IF(OR(I35="OPEN",I35="PARTIALLY PAID"),(G35-L35)*M35,0) -> 18108442 | P35: =IF(O35>0,MAX(0,DATE(2025,3,31)-E35),0) -> 0 | Q35: =IF(H35="","",H35-E35) | R35: =IF(O35=0,"Not open",IF(P35=0,"Not yet due",IF(P35<=30,"1-30",IF(P35<=60,"31-60",IF(P35<=90,"61-90","90+"))))) -> Not yet due
A36: INV002607 | B36: C0039 | C36: BU04 | D36: 45726 | E36: 45786 | F36: INR | G36: 17905495 | I36: OPEN | J36: N | L36: 0 | M36: =IF(F36="INR",1,INDEX('rates'!$B$2:$C$522,MATCH(D36,'rates'!$A$2:$A$522,1),MATCH(F36&"/INR",'rates'!$B$1:$C$1,0))) -> 1 | N36: =G36*M36 -> 17905495 | O36: =IF(OR(I36="OPEN",I36="PARTIALLY PAID"),(G36-L36)*M36,0) -> 17905495 | P36: =IF(O36>0,MAX(0,DATE(2025,3,31)-E36),0) -> 0 | Q36: =IF(H36="","",H36-E36) | R36: =IF(O36=0,"Not open",IF(P36=0,"Not yet due",IF(P36<=30,"1-30",IF(P36<=60,"31-60",IF(P36<=90,"61-90","90+"))))) -> Not yet due
A37: INV002687 | B37: C0061 | C37: BU02 | D37: 45744 | E37: 45834 | F37: INR | G37: 17390108 | I37: OPEN | J37: N | L37: 0 | M37: =IF(F37="INR",1,INDEX('rates'!$B$2:$C$522,MATCH(D37,'rates'!$A$2:$A$522,1),MATCH(F37&"/INR",'rates'!$B$1:$C$1,0))) -> 1 | N37: =G37*M37 -> 17390108 | O37: =IF(OR(I37="OPEN",I37="PARTIALLY PAID"),(G37-L37)*M37,0) -> 17390108 | P37: =IF(O37>0,MAX(0,DATE(2025,3,31)-E37),0) -> 0 | Q37: =IF(H37="","",H37-E37) | R37: =IF(O37=0,"Not open",IF(P37=0,"Not yet due",IF(P37<=30,"1-30",IF(P37<=60,"31-60",IF(P37<=90,"61-90","90+"))))) -> Not yet due
A38: INV002504 | B38: C0146 | C38: BU01 | D38: 45700 | E38: 45760 | F38: USD | G38: 199230.33 | I38: OPEN | J38: Y | K38: 87.1897 | L38: 0 | M38: =IF(F38="INR",1,INDEX('rates'!$B$2:$C$522,MATCH(D38,'rates'!$A$2:$A$522,1),MATCH(F38&"/INR",'rates'!$B$1:$C$1,0))) -> 86.9 | N38: =G38*M38 -> 17313116 | O38: =IF(OR(I38="OPEN",I38="PARTIALLY PAID"),(G38-L38)*M38,0) -> 17313116 | P38: =IF(O38>0,MAX(0,DATE(2025,3,31)-E38),0) -> 0 | Q38: =IF(H38="","",H38-E38) | R38: =IF(O38=0,"Not open",IF(P38=0,"Not yet due",IF(P38<=30,"1-30",IF(P38<=60,"31-60",IF(P38<=90,"61-90","90+"))))) -> Not yet due
A39: INV002471 | B39: C0166 | C39: BU05 | D39: 45692 | E39: 45782 | F39: INR | G39: 16989427 | I39: OPEN | J39: N | L39: 0 | M39: =IF(F39="INR",1,INDEX('rates'!$B$2:$C$522,MATCH(D39,'rates'!$A$2:$A$522,1),MATCH(F39&"/INR",'rates'!$B$1:$C$1,0))) -> 1 | N39: =G39*M39 -> 16989427 | O39: =IF(OR(I39="OPEN",I39="PARTIALLY PAID"),(G39-L39)*M39,0) -> 16989427 | P39: =IF(O39>0,MAX(0,DATE(2025,3,31)-E39),0) -> 0 | Q39: =IF(H39="","",H39-E39) | R39: =IF(O39=0,"Not open",IF(P39=0,"Not yet due",IF(P39<=30,"1-30",IF(P39<=60,"31-60",IF(P39<=90,"61-90","90+"))))) -> Not yet due
A40: INV002518 | B40: C0102 | C40: BU03 | D40: 45702 | E40: 45762 | F40: USD | G40: 186557.27 | I40: OPEN | J40: N | L40: 0 | M40: =IF(F40="INR",1,INDEX('rates'!$B$2:$C$522,MATCH(D40,'rates'!$A$2:$A$522,1),MATCH(F40&"/INR",'rates'!$B$1:$C$1,0))) -> 86.82 | N40: =G40*M40 -> 16196902 | O40: =IF(OR(I40="OPEN",I40="PARTIALLY PAID"),(G40-L40)*M40,0) -> 16196902 | P40: =IF(O40>0,MAX(0,DATE(2025,3,31)-E40),0) -> 0 | Q40: =IF(H40="","",H40-E40) | R40: =IF(O40=0,"Not open",IF(P40=0,"Not yet due",IF(P40<=30,"1-30",IF(P40<=60,"31-60",IF(P40<=90,"61-90","90+"))))) -> Not yet due
A41: INV002592 | B41: C0112 | C41: BU03 | D41: 45722 | E41: 45767 | F41: INR | G41: 16167557 | I41: OPEN | J41: N | L41: 0 | M41: =IF(F41="INR",1,INDEX('rates'!$B$2:$C$522,MATCH(D41,'rates'!$A$2:$A$522,1),MATCH(F41&"/INR",'rates'!$B$1:$C$1,0))) -> 1 | N41: =G41*M41 -> 16167557 | O41: =IF(OR(I41="OPEN",I41="PARTIALLY PAID"),(G41-L41)*M41,0) -> 16167557 | P41: =IF(O41>0,MAX(0,DATE(2025,3,31)-E41),0) -> 0 | Q41: =IF(H41="","",H41-E41) | R41: =IF(O41=0,"Not open",IF(P41=0,"Not yet due",IF(P41<=30,"1-30",IF(P41<=60,"31-60",IF(P41<=90,"61-90","90+"))))) -> Not yet due
A42: INV000768 | B42: C0236 | C42: BU02 | D42: 45248 | E42: 45308 | F42: EUR | G42: 390064.79 | H42: 45336 | I42: PARTIALLY PAID | J42: N | L42: 213178.92 | M42: =IF(F42="INR",1,INDEX('rates'!$B$2:$C$522,MATCH(D42,'rates'!$A$2:$A$522,1),MATCH(F42&"/INR",'rates'!$B$1:$C$1,0))) -> 90.5677 | N42: =G42*M42 -> 35327271 | O42: =IF(OR(I42="OPEN",I42="PARTIALLY PAID"),(G42-L42)*M42,0) -> 16020146 | P42: =IF(O42>0,MAX(0,DATE(2025,3,31)-E42),0) -> 439 | Q42: =IF(H42="","",H42-E42) -> 28 | R42: =IF(O42=0,"Not open",IF(P42=0,"Not yet due",IF(P42<=30,"1-30",IF(P42<=60,"31-60",IF(P42<=90,"61-90","90+"))))) -> 90+
A43: INV001646 | B43: C0029 | C43: BU02 | D43: 45479 | E43: 45569 | F43: INR | G43: 41067334 | H43: 45569 | I43: PARTIALLY PAID | J43: N | L43: 25770994 | M43: =IF(F43="INR",1,INDEX('rates'!$B$2:$C$522,MATCH(D43,'rates'!$A$2:$A$522,1),MATCH(F43&"/INR",'rates'!$B$1:$C$1,0))) -> 1 | N43: =G43*M43 -> 41067334 | O43: =IF(OR(I43="OPEN",I43="PARTIALLY PAID"),(G43-L43)*M43,0) -> 15296340 | P43: =IF(O43>0,MAX(0,DATE(2025,3,31)-E43),0) -> 178 | Q43: =IF(H43="","",H43-E43) -> 0 | R43: =IF(O43=0,"Not open",IF(P43=0,"Not yet due",IF(P43<=30,"1-30",IF(P43<=60,"31-60",IF(P43<=90,"61-90","90+"))))) -> 90+
A44: INV002625 | B44: C0183 | C44: BU04 | D44: 45730 | E44: 45820 | F44: INR | G44: 15158950 | I44: OPEN | J44: N | L44: 0 | M44: =IF(F44="INR",1,INDEX('rates'!$B$2:$C$522,MATCH(D44,'rates'!$A$2:$A$522,1),MATCH(F44&"/INR",'rates'!$B$1:$C$1,0))) -> 1 | N44: =G44*M44 -> 15158950 | O44: =IF(OR(I44="OPEN",I44="PARTIALLY PAID"),(G44-L44)*M44,0) -> 15158950 | P44: =IF(O44>0,MAX(0,DATE(2025,3,31)-E44),0) -> 0 | Q44: =IF(H44="","",H44-E44) | R44: =IF(O44=0,"Not open",IF(P44=0,"Not yet due",IF(P44<=30,"1-30",IF(P44<=60,"31-60",IF(P44<=90,"61-90","90+"))))) -> Not yet due
A45: INV002612 | B45: C0073 | C45: BU02 | D45: 45727 | E45: 45757 | F45: USD | G45: 173838.35 | I45: OPEN | J45: N | L45: 0 | M45: =IF(F45="INR",1,INDEX('rates'!$B$2:$C$522,MATCH(D45,'rates'!$A$2:$A$522,1),MATCH(F45&"/INR",'rates'!$B$1:$C$1,0))) -> 87.16 | N45: =G45*M45 -> 15151751 | O45: =IF(OR(I45="OPEN",I45="PARTIALLY PAID"),(G45-L45)*M45,0) -> 15151751 | P45: =IF(O45>0,MAX(0,DATE(2025,3,31)-E45),0) -> 0 | Q45: =IF(H45="","",H45-E45) | R45: =IF(O45=0,"Not open",IF(P45=0,"Not yet due",IF(P45<=30,"1-30",IF(P45<=60,"31-60",IF(P45<=90,"61-90","90+"))))) -> Not yet due
A46: INV002563 | B46: C0166 | C46: BU03 | D46: 45715 | E46: 45805 | F46: INR | G46: 14985083 | I46: OPEN | J46: N | L46: 0 | M46: =IF(F46="INR",1,INDEX('rates'!$B$2:$C$522,MATCH(D46,'rates'!$A$2:$A$522,1),MATCH(F46&"/INR",'rates'!$B$1:$C$1,0))) -> 1 | N46: =G46*M46 -> 14985083 | O46: =IF(OR(I46="OPEN",I46="PARTIALLY PAID"),(G46-L46)*M46,0) -> 14985083 | P46: =IF(O46>0,MAX(0,DATE(2025,3,31)-E46),0) -> 0 | Q46: =IF(H46="","",H46-E46) | R46: =IF(O46=0,"Not open",IF(P46=0,"Not yet due",IF(P46<=30,"1-30",IF(P46<=60,"31-60",IF(P46<=90,"61-90","90+"))))) -> Not yet due
A47: INV002624 | B47: C0099 | C47: BU01 | D47: 45730 | E47: 45790 | F47: EUR | G47: 152864.47 | I47: OPEN | J47: Y | K47: 94.7756 | L47: 0 | M47: =IF(F47="INR",1,INDEX('rates'!$B$2:$C$522,MATCH(D47,'rates'!$A$2:$A$522,1),MATCH(F47&"/INR",'rates'!$B$1:$C$1,0))) -> 94.5864 | N47: =G47*M47 -> 14458900 | O47: =IF(OR(I47="OPEN",I47="PARTIALLY PAID"),(G47-L47)*M47,0) -> 14458900 | P47: =IF(O47>0,MAX(0,DATE(2025,3,31)-E47),0) -> 0 | Q47: =IF(H47="","",H47-E47) | R47: =IF(O47=0,"Not open",IF(P47=0,"Not yet due",IF(P47<=30,"1-30",IF(P47<=60,"31-60",IF(P47<=90,"61-90","90+"))))) -> Not yet due
A48: INV002571 | B48: C0063 | C48: BU05 | D48: 45717 | E48: 45777 | F48: INR | G48: 14140436 | I48: OPEN | J48: N | L48: 0 | M48: =IF(F48="INR",1,INDEX('rates'!$B$2:$C$522,MATCH(D48,'rates'!$A$2:$A$522,1),MATCH(F48&"/INR",'rates'!$B$1:$C$1,0))) -> 1 | N48: =G48*M48 -> 14140436 | O48: =IF(OR(I48="OPEN",I48="PARTIALLY PAID"),(G48-L48)*M48,0) -> 14140436 | P48: =IF(O48>0,MAX(0,DATE(2025,3,31)-E48),0) -> 0 | Q48: =IF(H48="","",H48-E48) | R48: =IF(O48=0,"Not open",IF(P48=0,"Not yet due",IF(P48<=30,"1-30",IF(P48<=60,"31-60",IF(P48<=90,"61-90","90+"))))) -> Not yet due
A49: INV002278 | B49: C0166 | C49: BU03 | D49: 45643 | E49: 45733 | F49: INR | G49: 13783437 | I49: OPEN | J49: N | L49: 0 | M49: =IF(F49="INR",1,INDEX('rates'!$B$2:$C$522,MATCH(D49,'rates'!$A$2:$A$522,1),MATCH(F49&"/INR",'rates'!$B$1:$C$1,0))) -> 1 | N49: =G49*M49 -> 13783437 | O49: =IF(OR(I49="OPEN",I49="PARTIALLY PAID"),(G49-L49)*M49,0) -> 13783437 | P49: =IF(O49>0,MAX(0,DATE(2025,3,31)-E49),0) -> 14 | Q49: =IF(H49="","",H49-E49) | R49: =IF(O49=0,"Not open",IF(P49=0,"Not yet due",IF(P49<=30,"1-30",IF(P49<=60,"31-60",IF(P49<=90,"61-90","90+"))))) -> 1-30
A50: INV002596 | B50: C0171 | C50: BU01 | D50: 45723 | E50: 45813 | F50: USD | G50: 155196.03 | I50: OPEN | J50: Y | K50: 87.3144 | L50: 0 | M50: =IF(F50="INR",1,INDEX('rates'!$B$2:$C$522,MATCH(D50,'rates'!$A$2:$A$522,1),MATCH(F50&"/INR",'rates'!$B$1:$C$1,0))) -> 86.88 | N50: =G50*M50 -> 13483431 | O50: =IF(OR(I50="OPEN",I50="PARTIALLY PAID"),(G50-L50)*M50,0) -> 13483431 | P50: =IF(O50>0,MAX(0,DATE(2025,3,31)-E50),0) -> 0 | Q50: =IF(H50="","",H50-E50) | R50: =IF(O50=0,"Not open",IF(P50=0,"Not yet due",IF(P50<=30,"1-30",IF(P50<=60,"31-60",IF(P50<=90,"61-90","90+"))))) -> Not yet due
A51: INV002589 | B51: C0166 | C51: BU03 | D51: 45721 | E51: 45811 | F51: INR | G51: 13461092 | I51: OPEN | J51: N | L51: 0 | M51: =IF(F51="INR",1,INDEX('rates'!$B$2:$C$522,MATCH(D51,'rates'!$A$2:$A$522,1),MATCH(F51&"/INR",'rates'!$B$1:$C$1,0))) -> 1 | N51: =G51*M51 -> 13461092 | O51: =IF(OR(I51="OPEN",I51="PARTIALLY PAID"),(G51-L51)*M51,0) -> 13461092 | P51: =IF(O51>0,MAX(0,DATE(2025,3,31)-E51),0) -> 0 | Q51: =IF(H51="","",H51-E51) | R51: =IF(O51=0,"Not open",IF(P51=0,"Not yet due",IF(P51<=30,"1-30",IF(P51<=60,"31-60",IF(P51<=90,"61-90","90+"))))) -> Not yet due
A52: INV001911 | B52: C0216 | C52: BU02 | D52: 45556 | E52: 45616 | F52: USD | G52: 159363.47 | I52: OPEN | J52: N | L52: 0 | M52: =IF(F52="INR",1,INDEX('rates'!$B$2:$C$522,MATCH(D52,'rates'!$A$2:$A$522,1),MATCH(F52&"/INR",'rates'!$B$1:$C$1,0))) -> 83.57 | N52: =G52*M52 -> 13318005 | O52: =IF(OR(I52="OPEN",I52="PARTIALLY PAID"),(G52-L52)*M52,0) -> 13318005 | P52: =IF(O52>0,MAX(0,DATE(2025,3,31)-E52),0) -> 131 | Q52: =IF(H52="","",H52-E52) | R52: =IF(O52=0,"Not open",IF(P52=0,"Not yet due",IF(P52<=30,"1-30",IF(P52<=60,"31-60",IF(P52<=90,"61-90","90+"))))) -> 90+
A53: INV002672 | B53: C0144 | C53: BU05 | D53: 45740 | E53: 45785 | F53: INR | G53: 13196134 | I53: OPEN | J53: N | L53: 0 | M53: =IF(F53="INR",1,INDEX('rates'!$B$2:$C$522,MATCH(D53,'rates'!$A$2:$A$522,1),MATCH(F53&"/INR",'rates'!$B$1:$C$1,0))) -> 1 | N53: =G53*M53 -> 13196134 | O53: =IF(OR(I53="OPEN",I53="PARTIALLY PAID"),(G53-L53)*M53,0) -> 13196134 | P53: =IF(O53>0,MAX(0,DATE(2025,3,31)-E53),0) -> 0 | Q53: =IF(H53="","",H53-E53) | R53: =IF(O53=0,"Not open",IF(P53=0,"Not yet due",IF(P53<=30,"1-30",IF(P53<=60,"31-60",IF(P53<=90,"61-90","90+"))))) -> Not yet due
A54: INV002603 | B54: C0111 | C54: BU01 | D54: 45724 | E54: 45814 | F54: EUR | G54: 137648.45 | I54: OPEN | J54: N | L54: 0 | M54: =IF(F54="INR",1,INDEX('rates'!$B$2:$C$522,MATCH(D54,'rates'!$A$2:$A$522,1),MATCH(F54&"/INR",'rates'!$B$1:$C$1,0))) -> 94.343 | N54: =G54*M54 -> 12986168 | O54: =IF(OR(I54="OPEN",I54="PARTIALLY PAID"),(G54-L54)*M54,0) -> 12986168 | P54: =IF(O54>0,MAX(0,DATE(2025,3,31)-E54),0) -> 0 | Q54: =IF(H54="","",H54-E54) | R54: =IF(O54=0,"Not open",IF(P54=0,"Not yet due",IF(P54<=30,"1-30",IF(P54<=60,"31-60",IF(P54<=90,"61-90","90+"))))) -> Not yet due
A55: INV002475 | B55: C0073 | C55: BU02 | D55: 45693 | E55: 45723 | F55: USD | G55: 149073.01 | I55: OPEN | J55: N | L55: 0 | M55: =IF(F55="INR",1,INDEX('rates'!$B$2:$C$522,MATCH(D55,'rates'!$A$2:$A$522,1),MATCH(F55&"/INR",'rates'!$B$1:$C$1,0))) -> 87.08 | N55: =G55*M55 -> 12981278 | O55: =IF(OR(I55="OPEN",I55="PARTIALLY PAID"),(G55-L55)*M55,0) -> 12981278 | P55: =IF(O55>0,MAX(0,DATE(2025,3,31)-E55),0) -> 24 | Q55: =IF(H55="","",H55-E55) | R55: =IF(O55=0,"Not open",IF(P55=0,"Not yet due",IF(P55<=30,"1-30",IF(P55<=60,"31-60",IF(P55<=90,"61-90","90+"))))) -> 1-30
A56: INV002635 | B56: C0128 | C56: BU04 | D56: 45731 | E56: 45761 | F56: INR | G56: 12781394 | I56: OPEN | J56: N | L56: 0 | M56: =IF(F56="INR",1,INDEX('rates'!$B$2:$C$522,MATCH(D56,'rates'!$A$2:$A$522,1),MATCH(F56&"/INR",'rates'!$B$1:$C$1,0))) -> 1 | N56: =G56*M56 -> 12781394 | O56: =IF(OR(I56="OPEN",I56="PARTIALLY PAID"),(G56-L56)*M56,0) -> 12781394 | P56: =IF(O56>0,MAX(0,DATE(2025,3,31)-E56),0) -> 0 | Q56: =IF(H56="","",H56-E56) | R56: =IF(O56=0,"Not open",IF(P56=0,"Not yet due",IF(P56<=30,"1-30",IF(P56<=60,"31-60",IF(P56<=90,"61-90","90+"))))) -> Not yet due
A57: INV002553 | B57: C0099 | C57: BU01 | D57: 45710 | E57: 45770 | F57: EUR | G57: 140482.35 | I57: OPEN | J57: N | L57: 0 | M57: =IF(F57="INR",1,INDEX('rates'!$B$2:$C$522,MATCH(D57,'rates'!$A$2:$A$522,1),MATCH(F57&"/INR",'rates'!$B$1:$C$1,0))) -> 90.6448 | N57: =G57*M57 -> 12733995 | O57: =IF(OR(I57="OPEN",I57="PARTIALLY PAID"),(G57-L57)*M57,0) -> 12733995 | P57: =IF(O57>0,MAX(0,DATE(2025,3,31)-E57),0) -> 0 | Q57: =IF(H57="","",H57-E57) | R57: =IF(O57=0,"Not open",IF(P57=0,"Not yet due",IF(P57<=30,"1-30",IF(P57<=60,"31-60",IF(P57<=90,"61-90","90+"))))) -> Not yet due
A58: INV002565 | B58: C0216 | C58: BU02 | D58: 45715 | E58: 45775 | F58: USD | G58: 145463.12 | I58: OPEN | J58: N | L58: 0 | M58: =IF(F58="INR",1,INDEX('rates'!$B$2:$C$522,MATCH(D58,'rates'!$A$2:$A$522,1),MATCH(F58&"/INR",'rates'!$B$1:$C$1,0))) -> 87.17 | N58: =G58*M58 -> 12680020 | O58: =IF(OR(I58="OPEN",I58="PARTIALLY PAID"),(G58-L58)*M58,0) -> 12680020 | P58: =IF(O58>0,MAX(0,DATE(2025,3,31)-E58),0) -> 0 | Q58: =IF(H58="","",H58-E58) | R58: =IF(O58=0,"Not open",IF(P58=0,"Not yet due",IF(P58<=30,"1-30",IF(P58<=60,"31-60",IF(P58<=90,"61-90","90+"))))) -> Not yet due
A59: INV002468 | B59: C0173 | C59: BU03 | D59: 45691 | E59: 45751 | F59: EUR | G59: 139484.45 | I59: OPEN | J59: Y | K59: 89.7844 | L59: 0 | M59: =IF(F59="INR",1,INDEX('rates'!$B$2:$C$522,MATCH(D59,'rates'!$A$2:$A$522,1),MATCH(F59&"/INR",'rates'!$B$1:$C$1,0))) -> 89.6052 | N59: =G59*M59 -> 12498532 | O59: =IF(OR(I59="OPEN",I59="PARTIALLY PAID"),(G59-L59)*M59,0) -> 12498532 | P59: =IF(O59>0,MAX(0,DATE(2025,3,31)-E59),0) -> 0 | Q59: =IF(H59="","",H59-E59) | R59: =IF(O59=0,"Not open",IF(P59=0,"Not yet due",IF(P59<=30,"1-30",IF(P59<=60,"31-60",IF(P59<=90,"61-90","90+"))))) -> Not yet due
A60: INV002642 | B60: C0059 | C60: BU01 | D60: 45733 | E60: 45763 | F60: INR | G60: 12371795 | I60: OPEN | J60: N | L60: 0 | M60: =IF(F60="INR",1,INDEX('rates'!$B$2:$C$522,MATCH(D60,'rates'!$A$2:$A$522,1),MATCH(F60&"/INR",'rates'!$B$1:$C$1,0))) -> 1 | N60: =G60*M60 -> 12371795 | O60: =IF(OR(I60="OPEN",I60="PARTIALLY PAID"),(G60-L60)*M60,0) -> 12371795 | P60: =IF(O60>0,MAX(0,DATE(2025,3,31)-E60),0) -> 0 | Q60: =IF(H60="","",H60-E60) | R60: =IF(O60=0,"Not open",IF(P60=0,"Not yet due",IF(P60<=30,"1-30",IF(P60<=60,"31-60",IF(P60<=90,"61-90","90+"))))) -> Not yet due
A61: INV002529 | B61: C0207 | C61: BU03 | D61: 45703 | E61: 45763 | F61: INR | G61: 12349448 | I61: OPEN | J61: N | L61: 0 | M61: =IF(F61="INR",1,INDEX('rates'!$B$2:$C$522,MATCH(D61,'rates'!$A$2:$A$522,1),MATCH(F61&"/INR",'rates'!$B$1:$C$1,0))) -> 1 | N61: =G61*M61 -> 12349448 | O61: =IF(OR(I61="OPEN",I61="PARTIALLY PAID"),(G61-L61)*M61,0) -> 12349448 | P61: =IF(O61>0,MAX(0,DATE(2025,3,31)-E61),0) -> 0 | Q61: =IF(H61="","",H61-E61) | R61: =IF(O61=0,"Not open",IF(P61=0,"Not yet due",IF(P61<=30,"1-30",IF(P61<=60,"31-60",IF(P61<=90,"61-90","90+"))))) -> Not yet due
A62: INV002285 | B62: C0115 | C62: BU02 | D62: 45644 | E62: 45704 | F62: EUR | G62: 138689.61 | I62: OPEN | J62: N | L62: 0 | M62: =IF(F62="INR",1,INDEX('rates'!$B$2:$C$522,MATCH(D62,'rates'!$A$2:$A$522,1),MATCH(F62&"/INR",'rates'!$B$1:$C$1,0))) -> 88.9342 | N62: =G62*M62 -> 12334250 | O62: =IF(OR(I62="OPEN",I62="PARTIALLY PAID"),(G62-L62)*M62,0) -> 12334250 | P62: =IF(O62>0,MAX(0,DATE(2025,3,31)-E62),0) -> 43 | Q62: =IF(H62="","",H62-E62) | R62: =IF(O62=0,"Not open",IF(P62=0,"Not yet due",IF(P62<=30,"1-30",IF(P62<=60,"31-60",IF(P62<=90,"61-90","90+"))))) -> 31-60
A63: INV002360 | B63: C0107 | C63: BU02 | D63: 45664 | E63: 45694 | F63: INR | G63: 12314780 | I63: OPEN | J63: N | L63: 0 | M63: =IF(F63="INR",1,INDEX('rates'!$B$2:$C$522,MATCH(D63,'rates'!$A$2:$A$522,1),MATCH(F63&"/INR",'rates'!$B$1:$C$1,0))) -> 1 | N63: =G63*M63 -> 12314780 | O63: =IF(OR(I63="OPEN",I63="PARTIALLY PAID"),(G63-L63)*M63,0) -> 12314780 | P63: =IF(O63>0,MAX(0,DATE(2025,3,31)-E63),0) -> 53 | Q63: =IF(H63="","",H63-E63) | R63: =IF(O63=0,"Not open",IF(P63=0,"Not yet due",IF(P63<=30,"1-30",IF(P63<=60,"31-60",IF(P63<=90,"61-90","90+"))))) -> 31-60
A64: INV002483 | B64: C0107 | C64: BU02 | D64: 45694 | E64: 45724 | F64: INR | G64: 12293686 | I64: OPEN | J64: N | L64: 0 | M64: =IF(F64="INR",1,INDEX('rates'!$B$2:$C$522,MATCH(D64,'rates'!$A$2:$A$522,1),MATCH(F64&"/INR",'rates'!$B$1:$C$1,0))) -> 1 | N64: =G64*M64 -> 12293686 | O64: =IF(OR(I64="OPEN",I64="PARTIALLY PAID"),(G64-L64)*M64,0) -> 12293686 | P64: =IF(O64>0,MAX(0,DATE(2025,3,31)-E64),0) -> 23 | Q64: =IF(H64="","",H64-E64) | R64: =IF(O64=0,"Not open",IF(P64=0,"Not yet due",IF(P64<=30,"1-30",IF(P64<=60,"31-60",IF(P64<=90,"61-90","90+"))))) -> 1-30
A65: INV002535 | B65: C0076 | C65: BU04 | D65: 45705 | E65: 45765 | F65: INR | G65: 12075062 | I65: OPEN | J65: N | L65: 0 | M65: =IF(F65="INR",1,INDEX('rates'!$B$2:$C$522,MATCH(D65,'rates'!$A$2:$A$522,1),MATCH(F65&"/INR",'rates'!$B$1:$C$1,0))) -> 1 | N65: =G65*M65 -> 12075062 | O65: =IF(OR(I65="OPEN",I65="PARTIALLY PAID"),(G65-L65)*M65,0) -> 12075062 | P65: =IF(O65>0,MAX(0,DATE(2025,3,31)-E65),0) -> 0 | Q65: =IF(H65="","",H65-E65) | R65: =IF(O65=0,"Not open",IF(P65=0,"Not yet due",IF(P65<=30,"1-30",IF(P65<=60,"31-60",IF(P65<=90,"61-90","90+"))))) -> Not yet due
A66: INV002593 | B66: C0143 | C66: BU04 | D66: 45722 | E66: 45752 | F66: INR | G66: 11966989 | I66: OPEN | J66: N | L66: 0 | M66: =IF(F66="INR",1,INDEX('rates'!$B$2:$C$522,MATCH(D66,'rates'!$A$2:$A$522,1),MATCH(F66&"/INR",'rates'!$B$1:$C$1,0))) -> 1 | N66: =G66*M66 -> 11966989 | O66: =IF(OR(I66="OPEN",I66="PARTIALLY PAID"),(G66-L66)*M66,0) -> 11966989 | P66: =IF(O66>0,MAX(0,DATE(2025,3,31)-E66),0) -> 0 | Q66: =IF(H66="","",H66-E66) | R66: =IF(O66=0,"Not open",IF(P66=0,"Not yet due",IF(P66<=30,"1-30",IF(P66<=60,"31-60",IF(P66<=90,"61-90","90+"))))) -> Not yet due
A67: INV002588 | B67: C0057 | C67: BU01 | D67: 45721 | E67: 45751 | F67: INR | G67: 11946647 | I67: OPEN | J67: N | L67: 0 | M67: =IF(F67="INR",1,INDEX('rates'!$B$2:$C$522,MATCH(D67,'rates'!$A$2:$A$522,1),MATCH(F67&"/INR",'rates'!$B$1:$C$1,0))) -> 1 | N67: =G67*M67 -> 11946647 | O67: =IF(OR(I67="OPEN",I67="PARTIALLY PAID"),(G67-L67)*M67,0) -> 11946647 | P67: =IF(O67>0,MAX(0,DATE(2025,3,31)-E67),0) -> 0 | Q67: =IF(H67="","",H67-E67) | R67: =IF(O67=0,"Not open",IF(P67=0,"Not yet due",IF(P67<=30,"1-30",IF(P67<=60,"31-60",IF(P67<=90,"61-90","90+"))))) -> Not yet due
A68: INV002338 | B68: C0198 | C68: BU01 | D68: 45658 | E68: 45703 | F68: USD | G68: 139374.88 | I68: OPEN | J68: Y | K68: 85.7639 | L68: 0 | M68: =IF(F68="INR",1,INDEX('rates'!$B$2:$C$522,MATCH(D68,'rates'!$A$2:$A$522,1),MATCH(F68&"/INR",'rates'!$B$1:$C$1,0))) -> 85.55 | N68: =G68*M68 -> 11923521 | O68: =IF(OR(I68="OPEN",I68="PARTIALLY PAID"),(G68-L68)*M68,0) -> 11923521 | P68: =IF(O68>0,MAX(0,DATE(2025,3,31)-E68),0) -> 44 | Q68: =IF(H68="","",H68-E68) | R68: =IF(O68=0,"Not open",IF(P68=0,"Not yet due",IF(P68<=30,"1-30",IF(P68<=60,"31-60",IF(P68<=90,"61-90","90+"))))) -> 31-60
A69: INV002466 | B69: C0111 | C69: BU01 | D69: 45691 | E69: 45781 | F69: EUR | G69: 131624.31 | I69: OPEN | J69: Y | K69: 89.874 | L69: 0 | M69: =IF(F69="INR",1,INDEX('rates'!$B$2:$C$522,MATCH(D69,'rates'!$A$2:$A$522,1),MATCH(F69&"/INR",'rates'!$B$1:$C$1,0))) -> 89.6052 | N69: =G69*M69 -> 11794223 | O69: =IF(OR(I69="OPEN",I69="PARTIALLY PAID"),(G69-L69)*M69,0) -> 11794223 | P69: =IF(O69>0,MAX(0,DATE(2025,3,31)-E69),0) -> 0 | Q69: =IF(H69="","",H69-E69) | R69: =IF(O69=0,"Not open",IF(P69=0,"Not yet due",IF(P69<=30,"1-30",IF(P69<=60,"31-60",IF(P69<=90,"61-90","90+"))))) -> Not yet due
A70: INV002582 | B70: C0118 | C70: BU02 | D70: 45720 | E70: 45780 | F70: INR | G70: 11780041 | I70: OPEN | J70: N | L70: 0 | M70: =IF(F70="INR",1,INDEX('rates'!$B$2:$C$522,MATCH(D70,'rates'!$A$2:$A$522,1),MATCH(F70&"/INR",'rates'!$B$1:$C$1,0))) -> 1 | N70: =G70*M70 -> 11780041 | O70: =IF(OR(I70="OPEN",I70="PARTIALLY PAID"),(G70-L70)*M70,0) -> 11780041 | P70: =IF(O70>0,MAX(0,DATE(2025,3,31)-E70),0) -> 0 | Q70: =IF(H70="","",H70-E70) | R70: =IF(O70=0,"Not open",IF(P70=0,"Not yet due",IF(P70<=30,"1-30",IF(P70<=60,"31-60",IF(P70<=90,"61-90","90+"))))) -> Not yet due
A71: INV002694 | B71: C0134 | C71: BU04 | D71: 45745 | E71: 45835 | F71: INR | G71: 11495262 | I71: OPEN | J71: N | L71: 0 | M71: =IF(F71="INR",1,INDEX('rates'!$B$2:$C$522,MATCH(D71,'rates'!$A$2:$A$522,1),MATCH(F71&"/INR",'rates'!$B$1:$C$1,0))) -> 1 | N71: =G71*M71 -> 11495262 | O71: =IF(OR(I71="OPEN",I71="PARTIALLY PAID"),(G71-L71)*M71,0) -> 11495262 | P71: =IF(O71>0,MAX(0,DATE(2025,3,31)-E71),0) -> 0 | Q71: =IF(H71="","",H71-E71) | R71: =IF(O71=0,"Not open",IF(P71=0,"Not yet due",IF(P71<=30,"1-30",IF(P71<=60,"31-60",IF(P71<=90,"61-90","90+"))))) -> Not yet due
A72: INV001284 | B72: C0177 | C72: BU03 | D72: 45379 | E72: 45439 | F72: EUR | G72: 381431.82 | H72: 45448 | I72: PARTIALLY PAID | J72: N | L72: 254308.25 | M72: =IF(F72="INR",1,INDEX('rates'!$B$2:$C$522,MATCH(D72,'rates'!$A$2:$A$522,1),MATCH(F72&"/INR",'rates'!$B$1:$C$1,0))) -> 90.0263 | N72: =G72*M72 -> 34338895 | O72: =IF(OR(I72="OPEN",I72="PARTIALLY PAID"),(G72-L72)*M72,0) -> 11444465 | P72: =IF(O72>0,MAX(0,DATE(2025,3,31)-E72),0) -> 308 | Q72: =IF(H72="","",H72-E72) -> 9 | R72: =IF(O72=0,"Not open",IF(P72=0,"Not yet due",IF(P72<=30,"1-30",IF(P72<=60,"31-60",IF(P72<=90,"61-90","90+"))))) -> 90+
A73: INV002610 | B73: C0057 | C73: BU01 | D73: 45727 | E73: 45757 | F73: INR | G73: 11107252 | I73: OPEN | J73: N | L73: 0 | M73: =IF(F73="INR",1,INDEX('rates'!$B$2:$C$522,MATCH(D73,'rates'!$A$2:$A$522,1),MATCH(F73&"/INR",'rates'!$B$1:$C$1,0))) -> 1 | N73: =G73*M73 -> 11107252 | O73: =IF(OR(I73="OPEN",I73="PARTIALLY PAID"),(G73-L73)*M73,0) -> 11107252 | P73: =IF(O73>0,MAX(0,DATE(2025,3,31)-E73),0) -> 0 | Q73: =IF(H73="","",H73-E73) | R73: =IF(O73=0,"Not open",IF(P73=0,"Not yet due",IF(P73<=30,"1-30",IF(P73<=60,"31-60",IF(P73<=90,"61-90","90+"))))) -> Not yet due
A74: INV002453 | B74: C0099 | C74: BU01 | D74: 45687 | E74: 45747 | F74: EUR | G74: 119738.97 | I74: OPEN | J74: N | L74: 0 | M74: =IF(F74="INR",1,INDEX('rates'!$B$2:$C$522,MATCH(D74,'rates'!$A$2:$A$522,1),MATCH(F74&"/INR",'rates'!$B$1:$C$1,0))) -> 90.1851 | N74: =G74*M74 -> 10798671 | O74: =IF(OR(I74="OPEN",I74="PARTIALLY PAID"),(G74-L74)*M74,0) -> 10798671 | P74: =IF(O74>0,MAX(0,DATE(2025,3,31)-E74),0) -> 0 | Q74: =IF(H74="","",H74-E74) | R74: =IF(O74=0,"Not open",IF(P74=0,"Not yet due",IF(P74<=30,"1-30",IF(P74<=60,"31-60",IF(P74<=90,"61-90","90+"))))) -> Not yet due
A75: INV002674 | B75: C0244 | C75: BU01 | D75: 45740 | E75: 45800 | F75: INR | G75: 10617955 | I75: OPEN | J75: N | L75: 0 | M75: =IF(F75="INR",1,INDEX('rates'!$B$2:$C$522,MATCH(D75,'rates'!$A$2:$A$522,1),MATCH(F75&"/INR",'rates'!$B$1:$C$1,0))) -> 1 | N75: =G75*M75 -> 10617955 | O75: =IF(OR(I75="OPEN",I75="PARTIALLY PAID"),(G75-L75)*M75,0) -> 10617955 | P75: =IF(O75>0,MAX(0,DATE(2025,3,31)-E75),0) -> 0 | Q75: =IF(H75="","",H75-E75) | R75: =IF(O75=0,"Not open",IF(P75=0,"Not yet due",IF(P75<=30,"1-30",IF(P75<=60,"31-60",IF(P75<=90,"61-90","90+"))))) -> Not yet due
A76: INV001776 | B76: C0236 | C76: BU01 | D76: 45514 | E76: 45574 | F76: EUR | G76: 115404.11 | I76: OPEN | J76: Y | K76: 91.866 | L76: 0 | M76: =IF(F76="INR",1,INDEX('rates'!$B$2:$C$522,MATCH(D76,'rates'!$A$2:$A$522,1),MATCH(F76&"/INR",'rates'!$B$1:$C$1,0))) -> 91.6826 | N76: =G76*M76 -> 10580549 | O76: =IF(OR(I76="OPEN",I76="PARTIALLY PAID"),(G76-L76)*M76,0) -> 10580549 | P76: =IF(O76>0,MAX(0,DATE(2025,3,31)-E76),0) -> 173 | Q76: =IF(H76="","",H76-E76) | R76: =IF(O76=0,"Not open",IF(P76=0,"Not yet due",IF(P76<=30,"1-30",IF(P76<=60,"31-60",IF(P76<=90,"61-90","90+"))))) -> 90+
A77: INV000770 | B77: C0244 | C77: BU01 | D77: 45248 | E77: 45308 | F77: INR | G77: 32464060 | H77: 45362 | I77: PARTIALLY PAID | J77: N | L77: 21928675 | M77: =IF(F77="INR",1,INDEX('rates'!$B$2:$C$522,MATCH(D77,'rates'!$A$2:$A$522,1),MATCH(F77&"/INR",'rates'!$B$1:$C$1,0))) -> 1 | N77: =G77*M77 -> 32464060 | O77: =IF(OR(I77="OPEN",I77="PARTIALLY PAID"),(G77-L77)*M77,0) -> 10535385 | P77: =IF(O77>0,MAX(0,DATE(2025,3,31)-E77),0) -> 439 | Q77: =IF(H77="","",H77-E77) -> 54 | R77: =IF(O77=0,"Not open",IF(P77=0,"Not yet due",IF(P77<=30,"1-30",IF(P77<=60,"31-60",IF(P77<=90,"61-90","90+"))))) -> 90+
A78: INV002515 | B78: C0238 | C78: BU05 | D78: 45701 | E78: 45761 | F78: INR | G78: 10521766 | I78: OPEN | J78: N | L78: 0 | M78: =IF(F78="INR",1,INDEX('rates'!$B$2:$C$522,MATCH(D78,'rates'!$A$2:$A$522,1),MATCH(F78&"/INR",'rates'!$B$1:$C$1,0))) -> 1 | N78: =G78*M78 -> 10521766 | O78: =IF(OR(I78="OPEN",I78="PARTIALLY PAID"),(G78-L78)*M78,0) -> 10521766 | P78: =IF(O78>0,MAX(0,DATE(2025,3,31)-E78),0) -> 0 | Q78: =IF(H78="","",H78-E78) | R78: =IF(O78=0,"Not open",IF(P78=0,"Not yet due",IF(P78<=30,"1-30",IF(P78<=60,"31-60",IF(P78<=90,"61-90","90+"))))) -> Not yet due
A79: INV002680 | B79: C0198 | C79: BU01 | D79: 45741 | E79: 45786 | F79: USD | G79: 122313.13 | I79: OPEN | J79: Y | K79: 85.9844 | L79: 0 | M79: =IF(F79="INR",1,INDEX('rates'!$B$2:$C$522,MATCH(D79,'rates'!$A$2:$A$522,1),MATCH(F79&"/INR",'rates'!$B$1:$C$1,0))) -> 85.77 | N79: =G79*M79 -> 10490797 | O79: =IF(OR(I79="OPEN",I79="PARTIALLY PAID"),(G79-L79)*M79,0) -> 10490797 | P79: =IF(O79>0,MAX(0,DATE(2025,3,31)-E79),0) -> 0 | Q79: =IF(H79="","",H79-E79) | R79: =IF(O79=0,"Not open",IF(P79=0,"Not yet due",IF(P79<=30,"1-30",IF(P79<=60,"31-60",IF(P79<=90,"61-90","90+"))))) -> Not yet due
A80: INV002673 | B80: C0213 | C80: BU02 | D80: 45740 | E80: 45800 | F80: EUR | G80: 111413.55 | I80: OPEN | J80: N | L80: 0 | M80: =IF(F80="INR",1,INDEX('rates'!$B$2:$C$522,MATCH(D80,'rates'!$A$2:$A$522,1),MATCH(F80&"/INR",'rates'!$B$1:$C$1,0))) -> 92.3535 | N80: =G80*M80 -> 10289431 | O80: =IF(OR(I80="OPEN",I80="PARTIALLY PAID"),(G80-L80)*M80,0) -> 10289431 | P80: =IF(O80>0,MAX(0,DATE(2025,3,31)-E80),0) -> 0 | Q80: =IF(H80="","",H80-E80) | R80: =IF(O80=0,"Not open",IF(P80=0,"Not yet due",IF(P80<=30,"1-30",IF(P80<=60,"31-60",IF(P80<=90,"61-90","90+"))))) -> Not yet due
A81: INV002608 | B81: C0050 | C81: BU04 | D81: 45726 | E81: 45786 | F81: INR | G81: 10240098 | I81: OPEN | J81: N | L81: 0 | M81: =IF(F81="INR",1,INDEX('rates'!$B$2:$C$522,MATCH(D81,'rates'!$A$2:$A$522,1),MATCH(F81&"/INR",'rates'!$B$1:$C$1,0))) -> 1 | N81: =G81*M81 -> 10240098 | O81: =IF(OR(I81="OPEN",I81="PARTIALLY PAID"),(G81-L81)*M81,0) -> 10240098 | P81: =IF(O81>0,MAX(0,DATE(2025,3,31)-E81),0) -> 0 | Q81: =IF(H81="","",H81-E81) | R81: =IF(O81=0,"Not open",IF(P81=0,"Not yet due",IF(P81<=30,"1-30",IF(P81<=60,"31-60",IF(P81<=90,"61-90","90+"))))) -> Not yet due
A82: INV002528 | B82: C0207 | C82: BU03 | D82: 45703 | E82: 45763 | F82: INR | G82: 10160101 | I82: OPEN | J82: N | L82: 0 | M82: =IF(F82="INR",1,INDEX('rates'!$B$2:$C$522,MATCH(D82,'rates'!$A$2:$A$522,1),MATCH(F82&"/INR",'rates'!$B$1:$C$1,0))) -> 1 | N82: =G82*M82 -> 10160101 | O82: =IF(OR(I82="OPEN",I82="PARTIALLY PAID"),(G82-L82)*M82,0) -> 10160101 | P82: =IF(O82>0,MAX(0,DATE(2025,3,31)-E82),0) -> 0 | Q82: =IF(H82="","",H82-E82) | R82: =IF(O82=0,"Not open",IF(P82=0,"Not yet due",IF(P82<=30,"1-30",IF(P82<=60,"31-60",IF(P82<=90,"61-90","90+"))))) -> Not yet due
A83: INV002508 | B83: C0112 | C83: BU02 | D83: 45701 | E83: 45746 | F83: INR | G83: 10055994 | I83: OPEN | J83: N | L83: 0 | M83: =IF(F83="INR",1,INDEX('rates'!$B$2:$C$522,MATCH(D83,'rates'!$A$2:$A$522,1),MATCH(F83&"/INR",'rates'!$B$1:$C$1,0))) -> 1 | N83: =G83*M83 -> 10055994 | O83: =IF(OR(I83="OPEN",I83="PARTIALLY PAID"),(G83-L83)*M83,0) -> 10055994 | P83: =IF(O83>0,MAX(0,DATE(2025,3,31)-E83),0) -> 1 | Q83: =IF(H83="","",H83-E83) | R83: =IF(O83=0,"Not open",IF(P83=0,"Not yet due",IF(P83<=30,"1-30",IF(P83<=60,"31-60",IF(P83<=90,"61-90","90+"))))) -> 1-30
A84: INV002551 | B84: C0056 | C84: BU02 | D84: 45710 | E84: 45770 | F84: INR | G84: 10014966 | I84: OPEN | J84: N | L84: 0 | M84: =IF(F84="INR",1,INDEX('rates'!$B$2:$C$522,MATCH(D84,'rates'!$A$2:$A$522,1),MATCH(F84&"/INR",'rates'!$B$1:$C$1,0))) -> 1 | N84: =G84*M84 -> 10014966 | O84: =IF(OR(I84="OPEN",I84="PARTIALLY PAID"),(G84-L84)*M84,0) -> 10014966 | P84: =IF(O84>0,MAX(0,DATE(2025,3,31)-E84),0) -> 0 | Q84: =IF(H84="","",H84-E84) | R84: =IF(O84=0,"Not open",IF(P84=0,"Not yet due",IF(P84<=30,"1-30",IF(P84<=60,"31-60",IF(P84<=90,"61-90","90+"))))) -> Not yet due
A85: INV002375 | B85: C0236 | C85: BU01 | D85: 45666 | E85: 45726 | F85: EUR | G85: 113184.58 | I85: OPEN | J85: Y | K85: 88.6058 | L85: 0 | M85: =IF(F85="INR",1,INDEX('rates'!$B$2:$C$522,MATCH(D85,'rates'!$A$2:$A$522,1),MATCH(F85&"/INR",'rates'!$B$1:$C$1,0))) -> 88.4289 | N85: =G85*M85 -> 10008788 | O85: =IF(OR(I85="OPEN",I85="PARTIALLY PAID"),(G85-L85)*M85,0) -> 10008788 | P85: =IF(O85>0,MAX(0,DATE(2025,3,31)-E85),0) -> 21 | Q85: =IF(H85="","",H85-E85) | R85: =IF(O85=0,"Not open",IF(P85=0,"Not yet due",IF(P85<=30,"1-30",IF(P85<=60,"31-60",IF(P85<=90,"61-90","90+"))))) -> 1-30
A86: INV002072 | B86: C0236 | C86: BU02 | D86: 45591 | E86: 45651 | F86: EUR | G86: 108966.2 | I86: OPEN | J86: Y | K86: 91.0759 | L86: 0 | M86: =IF(F86="INR",1,INDEX('rates'!$B$2:$C$522,MATCH(D86,'rates'!$A$2:$A$522,1),MATCH(F86&"/INR",'rates'!$B$1:$C$1,0))) -> 90.8941 | N86: =G86*M86 -> 9904384.7 | O86: =IF(OR(I86="OPEN",I86="PARTIALLY PAID"),(G86-L86)*M86,0) -> 9904384.7 | P86: =IF(O86>0,MAX(0,DATE(2025,3,31)-E86),0) -> 96 | Q86: =IF(H86="","",H86-E86) | R86: =IF(O86=0,"Not open",IF(P86=0,"Not yet due",IF(P86<=30,"1-30",IF(P86<=60,"31-60",IF(P86<=90,"61-90","90+"))))) -> 90+
A87: INV000440 | B87: C0005 | C87: BU05 | D87: 45160 | E87: 45190 | F87: INR | G87: 20918941 | H87: 45193 | I87: PARTIALLY PAID | J87: N | L87: 11048579 | M87: =IF(F87="INR",1,INDEX('rates'!$B$2:$C$522,MATCH(D87,'rates'!$A$2:$A$522,1),MATCH(F87&"/INR",'rates'!$B$1:$C$1,0))) -> 1 | N87: =G87*M87 -> 20918941 | O87: =IF(OR(I87="OPEN",I87="PARTIALLY PAID"),(G87-L87)*M87,0) -> 9870361.8 | P87: =IF(O87>0,MAX(0,DATE(2025,3,31)-E87),0) -> 557 | Q87: =IF(H87="","",H87-E87) -> 3 | R87: =IF(O87=0,"Not open",IF(P87=0,"Not yet due",IF(P87<=30,"1-30",IF(P87<=60,"31-60",IF(P87<=90,"61-90","90+"))))) -> 90+
A88: INV002388 | B88: C0198 | C88: BU01 | D88: 45668 | E88: 45713 | F88: USD | G88: 114093.55 | I88: OPEN | J88: Y | K88: 86.1749 | L88: 0 | M88: =IF(F88="INR",1,INDEX('rates'!$B$2:$C$522,MATCH(D88,'rates'!$A$2:$A$522,1),MATCH(F88&"/INR",'rates'!$B$1:$C$1,0))) -> 85.96 | N88: =G88*M88 -> 9807481.6 | O88: =IF(OR(I88="OPEN",I88="PARTIALLY PAID"),(G88-L88)*M88,0) -> 9807481.6 | P88: =IF(O88>0,MAX(0,DATE(2025,3,31)-E88),0) -> 34 | Q88: =IF(H88="","",H88-E88) | R88: =IF(O88=0,"Not open",IF(P88=0,"Not yet due",IF(P88<=30,"1-30",IF(P88<=60,"31-60",IF(P88<=90,"61-90","90+"))))) -> 31-60
A89: INV002697 | B89: C0228 | C89: BU01 | D89: 45745 | E89: 45790 | F89: INR | G89: 9806641 | I89: OPEN | J89: N | L89: 0 | M89: =IF(F89="INR",1,INDEX('rates'!$B$2:$C$522,MATCH(D89,'rates'!$A$2:$A$522,1),MATCH(F89&"/INR",'rates'!$B$1:$C$1,0))) -> 1 | N89: =G89*M89 -> 9806641 | O89: =IF(OR(I89="OPEN",I89="PARTIALLY PAID"),(G89-L89)*M89,0) -> 9806641 | P89: =IF(O89>0,MAX(0,DATE(2025,3,31)-E89),0) -> 0 | Q89: =IF(H89="","",H89-E89) | R89: =IF(O89=0,"Not open",IF(P89=0,"Not yet due",IF(P89<=30,"1-30",IF(P89<=60,"31-60",IF(P89<=90,"61-90","90+"))))) -> Not yet due
A90: INV002568 | B90: C0197 | C90: BU04 | D90: 45716 | E90: 45761 | F90: INR | G90: 9705572 | I90: OPEN | J90: N | L90: 0 | M90: =IF(F90="INR",1,INDEX('rates'!$B$2:$C$522,MATCH(D90,'rates'!$A$2:$A$522,1),MATCH(F90&"/INR",'rates'!$B$1:$C$1,0))) -> 1 | N90: =G90*M90 -> 9705572 | O90: =IF(OR(I90="OPEN",I90="PARTIALLY PAID"),(G90-L90)*M90,0) -> 9705572 | P90: =IF(O90>0,MAX(0,DATE(2025,3,31)-E90),0) -> 0 | Q90: =IF(H90="","",H90-E90) | R90: =IF(O90=0,"Not open",IF(P90=0,"Not yet due",IF(P90<=30,"1-30",IF(P90<=60,"31-60",IF(P90<=90,"61-90","90+"))))) -> Not yet due
A91: INV001929 | B91: C0109 | C91: BU02 | D91: 45561 | E91: 45606 | F91: INR | G91: 26432704 | H91: 45621 | I91: PARTIALLY PAID | J91: N | L91: 16759492 | M91: =IF(F91="INR",1,INDEX('rates'!$B$2:$C$522,MATCH(D91,'rates'!$A$2:$A$522,1),MATCH(F91&"/INR",'rates'!$B$1:$C$1,0))) -> 1 | N91: =G91*M91 -> 26432704 | O91: =IF(OR(I91="OPEN",I91="PARTIALLY PAID"),(G91-L91)*M91,0) -> 9673212.1 | P91: =IF(O91>0,MAX(0,DATE(2025,3,31)-E91),0) -> 141 | Q91: =IF(H91="","",H91-E91) -> 15 | R91: =IF(O91=0,"Not open",IF(P91=0,"Not yet due",IF(P91<=30,"1-30",IF(P91<=60,"31-60",IF(P91<=90,"61-90","90+"))))) -> 90+
A92: INV002491 | B92: C0042 | C92: BU01 | D92: 45696 | E92: 45756 | F92: EUR | G92: 105993.68 | I92: OPEN | J92: Y | K92: 90.487 | L92: 0 | M92: =IF(F92="INR",1,INDEX('rates'!$B$2:$C$522,MATCH(D92,'rates'!$A$2:$A$522,1),MATCH(F92&"/INR",'rates'!$B$1:$C$1,0))) -> 90.3064 | N92: =G92*M92 -> 9571907.7 | O92: =IF(OR(I92="OPEN",I92="PARTIALLY PAID"),(G92-L92)*M92,0) -> 9571907.7 | P92: =IF(O92>0,MAX(0,DATE(2025,3,31)-E92),0) -> 0 | Q92: =IF(H92="","",H92-E92) | R92: =IF(O92=0,"Not open",IF(P92=0,"Not yet due",IF(P92<=30,"1-30",IF(P92<=60,"31-60",IF(P92<=90,"61-90","90+"))))) -> Not yet due
A93: INV000883 | B93: C0111 | C93: BU01 | D93: 45279 | E93: 45369 | F93: EUR | G93: 206606.18 | H93: 45383 | I93: PARTIALLY PAID | J93: Y | K93: 91.5806 | L93: 103364.91 | M93: =IF(F93="INR",1,INDEX('rates'!$B$2:$C$522,MATCH(D93,'rates'!$A$2:$A$522,1),MATCH(F93&"/INR",'rates'!$B$1:$C$1,0))) -> 91.3067 | N93: =G93*M93 -> 18864528 | O93: =IF(OR(I93="OPEN",I93="PARTIALLY PAID"),(G93-L93)*M93,0) -> 9426619.7 | P93: =IF(O93>0,MAX(0,DATE(2025,3,31)-E93),0) -> 378 | Q93: =IF(H93="","",H93-E93) -> 14 | R93: =IF(O93=0,"Not open",IF(P93=0,"Not yet due",IF(P93<=30,"1-30",IF(P93<=60,"31-60",IF(P93<=90,"61-90","90+"))))) -> 90+
A94: INV002646 | B94: C0071 | C94: BU02 | D94: 45734 | E94: 45794 | F94: USD | G94: 107904.77 | I94: OPEN | J94: Y | K94: 86.7883 | L94: 0 | M94: =IF(F94="INR",1,INDEX('rates'!$B$2:$C$522,MATCH(D94,'rates'!$A$2:$A$522,1),MATCH(F94&"/INR",'rates'!$B$1:$C$1,0))) -> 86.5 | N94: =G94*M94 -> 9333762.6 | O94: =IF(OR(I94="OPEN",I94="PARTIALLY PAID"),(G94-L94)*M94,0) -> 9333762.6 | P94: =IF(O94>0,MAX(0,DATE(2025,3,31)-E94),0) -> 0 | Q94: =IF(H94="","",H94-E94) | R94: =IF(O94=0,"Not open",IF(P94=0,"Not yet due",IF(P94<=30,"1-30",IF(P94<=60,"31-60",IF(P94<=90,"61-90","90+"))))) -> Not yet due
A95: INV002228 | B95: C0019 | C95: BU05 | D95: 45633 | E95: 45723 | F95: EUR | G95: 103874.64 | I95: OPEN | J95: N | L95: 0 | M95: =IF(F95="INR",1,INDEX('rates'!$B$2:$C$522,MATCH(D95,'rates'!$A$2:$A$522,1),MATCH(F95&"/INR",'rates'!$B$1:$C$1,0))) -> 89.4369 | N95: =G95*M95 -> 9290225.8 | O95: =IF(OR(I95="OPEN",I95="PARTIALLY PAID"),(G95-L95)*M95,0) -> 9290225.8 | P95: =IF(O95>0,MAX(0,DATE(2025,3,31)-E95),0) -> 24 | Q95: =IF(H95="","",H95-E95) | R95: =IF(O95=0,"Not open",IF(P95=0,"Not yet due",IF(P95<=30,"1-30",IF(P95<=60,"31-60",IF(P95<=90,"61-90","90+"))))) -> 1-30
A96: INV002623 | B96: C0072 | C96: BU03 | D96: 45730 | E96: 45820 | F96: EUR | G96: 97209.45 | I96: OPEN | J96: Y | K96: 94.8702 | L96: 0 | M96: =IF(F96="INR",1,INDEX('rates'!$B$2:$C$522,MATCH(D96,'rates'!$A$2:$A$522,1),MATCH(F96&"/INR",'rates'!$B$1:$C$1,0))) -> 94.5864 | N96: =G96*M96 -> 9194691.9 | O96: =IF(OR(I96="OPEN",I96="PARTIALLY PAID"),(G96-L96)*M96,0) -> 9194691.9 | P96: =IF(O96>0,MAX(0,DATE(2025,3,31)-E96),0) -> 0 | Q96: =IF(H96="","",H96-E96) | R96: =IF(O96=0,"Not open",IF(P96=0,"Not yet due",IF(P96<=30,"1-30",IF(P96<=60,"31-60",IF(P96<=90,"61-90","90+"))))) -> Not yet due
A97: INV002032 | B97: C0020 | C97: BU01 | D97: 45584 | E97: 45674 | F97: USD | G97: 108451.73 | I97: OPEN | J97: N | L97: 0 | M97: =IF(F97="INR",1,INDEX('rates'!$B$2:$C$522,MATCH(D97,'rates'!$A$2:$A$522,1),MATCH(F97&"/INR",'rates'!$B$1:$C$1,0))) -> 84.03 | N97: =G97*M97 -> 9113198.9 | O97: =IF(OR(I97="OPEN",I97="PARTIALLY PAID"),(G97-L97)*M97,0) -> 9113198.9 | P97: =IF(O97>0,MAX(0,DATE(2025,3,31)-E97),0) -> 73 | Q97: =IF(H97="","",H97-E97) | R97: =IF(O97=0,"Not open",IF(P97=0,"Not yet due",IF(P97<=30,"1-30",IF(P97<=60,"31-60",IF(P97<=90,"61-90","90+"))))) -> 61-90
A98: INV002643 | B98: C0069 | C98: BU05 | D98: 45733 | E98: 45763 | F98: INR | G98: 9069380 | I98: OPEN | J98: N | L98: 0 | M98: =IF(F98="INR",1,INDEX('rates'!$B$2:$C$522,MATCH(D98,'rates'!$A$2:$A$522,1),MATCH(F98&"/INR",'rates'!$B$1:$C$1,0))) -> 1 | N98: =G98*M98 -> 9069380 | O98: =IF(OR(I98="OPEN",I98="PARTIALLY PAID"),(G98-L98)*M98,0) -> 9069380 | P98: =IF(O98>0,MAX(0,DATE(2025,3,31)-E98),0) -> 0 | Q98: =IF(H98="","",H98-E98) | R98: =IF(O98=0,"Not open",IF(P98=0,"Not yet due",IF(P98<=30,"1-30",IF(P98<=60,"31-60",IF(P98<=90,"61-90","90+"))))) -> Not yet due
A99: INV002631 | B99: C0057 | C99: BU01 | D99: 45731 | E99: 45761 | F99: INR | G99: 9044576 | I99: OPEN | J99: N | L99: 0 | M99: =IF(F99="INR",1,INDEX('rates'!$B$2:$C$522,MATCH(D99,'rates'!$A$2:$A$522,1),MATCH(F99&"/INR",'rates'!$B$1:$C$1,0))) -> 1 | N99: =G99*M99 -> 9044576 | O99: =IF(OR(I99="OPEN",I99="PARTIALLY PAID"),(G99-L99)*M99,0) -> 9044576 | P99: =IF(O99>0,MAX(0,DATE(2025,3,31)-E99),0) -> 0 | Q99: =IF(H99="","",H99-E99) | R99: =IF(O99=0,"Not open",IF(P99=0,"Not yet due",IF(P99<=30,"1-30",IF(P99<=60,"31-60",IF(P99<=90,"61-90","90+"))))) -> Not yet due
A100: INV002550 | B100: C0033 | C100: BU05 | D100: 45710 | E100: 45800 | F100: USD | G100: 104117.25 | I100: OPEN | J100: Y | K100: 87.1335 | L100: 0 | M100: =IF(F100="INR",1,INDEX('rates'!$B$2:$C$522,MATCH(D100,'rates'!$A$2:$A$522,1),MATCH(F100&"/INR",'rates'!$B$1:$C$1,0))) -> 86.7 | N100: =G100*M100 -> 9026965.6 | O100: =IF(OR(I100="OPEN",I100="PARTIALLY PAID"),(G100-L100)*M100,0) -> 9026965.6 | P100: =IF(O100>0,MAX(0,DATE(2025,3,31)-E100),0) -> 0 | Q100: =IF(H100="","",H100-E100) | R100: =IF(O100=0,"Not open",IF(P100=0,"Not yet due",IF(P100<=30,"1-30",IF(P100<=60,"31-60",IF(P100<=90,"61-90","90+"))))) -> Not yet due
...

Sheet customers
A1: customer_id | B1: customer_name | C1: country | D1: billing_currency | E1: industry | F1: credit_rating | G1: credit_limit_inr | H1: onboarding_date | I1: limit_flag | J1: payment_terms_days
A2: C0001 | B2: Alpine Construction Industries Ltd | C2: India | D2: INR | E2: Construction | F2: BBB | G2: 7500000 | H2: 44020 | J2: 45
A3: C0002 | B3: Sahyadri Textiles Enterprises Pvt Ltd | C3: India | D3: INR | E3: Packaging | F3: BBB | G3: 28950000 | H3: 42009 | J3: 45
A4: C0003 | B4: Danube Industrial Plastics LLP | C4: India | D4: INR | E4: Packaging | F4: B | G4: 15500000 | H4: 42585 | J4: 45
A5: C0004 | B5: Aarav FMCG Plastics LLP | C5: India | D5: INR | E5: FMCG | F5: BBB | G5: 114250000 | H5: 43164 | J5: 45
A6: C0005 | B6: Everest Agri Products Enterprises Pvt Ltd | C6: India | D6: INR | E6: Industrial | F6: BBB | G6: 63550000 | H6: 44670 | J6: 30
A7: C0006 | B7: Danube Packaging GmbH | C7: Germany | D7: EUR | E7: Industrial | F7: A | G7: 98150000 | H7: 42648 | J7: 30
A8: C0007 | B8: Titan Packaging Inc | C8: USA | D8: USD | E8: Auto Components | F8: BB | G8: 42200000 | H8: 43958 | J8: 30
A9: C0008 | B9: Meridian Agri Products Industries Ltd | C9: India | D9: INR | E9: Electricals | F9: A | G9: 27050000 | H9: 43126 | J9: 90
A10: C0009 | B10: Gateway Healthcare Industries Ltd | C10: India | D10: INR | E10: Textiles | F10: AA | G10: 126700000 | H10: 44719 | J10: 60
A11: C0010 | B11: Titan Industrial Co. Ltd | C11: Vietnam | D11: USD | E11: Textiles | F11: BBB | G11: 43800000 | H11: 45021 | J11: 60
A12: C0011 | B12: Titan Electricals Industries Ltd | C12: India | D12: INR | E12: Packaging | F12: BB | G12: 35350000 | H12: 42324 | J12: 45
A13: C0012 | B13: Harbor Industrial SAS | C13: France | D13: EUR | E13: Auto Components | F13: Unrated | G13: 9500000 | H13: 43659 | J13: 60
... A19: C0018 | B19: Lakeshore Electricals Polymers Pvt Ltd | C19: India | D19: INR | E19: Electricals | F19: BBB | G19: 24800000 | H19: 44426 | J19: 30
A20: C0019 | B20: Redwood Textiles GmbH | C20: Germany | D20: EUR | E20: Consumer Goods | F20: BB | G20: 0 | H20: 43269 | I20: Invalid limit | J20: 90
A21: C0020 | B21: Maple Construction Co. Ltd | C21: Vietnam | D21: USD | E21: Agri Products | F21: CCC | G21: 10200000 | H21: 42469 | J21: 90
A22: C0021 | B22: Zephyr FMCG Inc | C22: USA | D22: USD | E22: Healthcare | F22: A | G22: 27950000 | H22: 43246 | J22: 90
A23: C0022 | B23: Harbor Textiles Industries Ltd | C23: India | D23: INR | E23: Auto Components | F23: BBB | G23: 27450000 | H23: 43333 | J23: 30
A24: C0023 | B24: Udaya Auto Components Industries Ltd | C24: India | D24: INR | E24: Auto Components | F24: CCC | G24: 5850000 | H24: 44865 | J24: 45
A25: C0024 | B25: Xenon Textiles Industries Ltd | C25: India | D25: INR | E25: Electricals | F25: AA | G25: 47650000 | H25: 43980 | J25: 30
A26: C0025 | B26: Lotus FMCG Pte Ltd | C26: Singapore | D26: USD | E26: Healthcare | F26: BB | G26: 64550000 | H26: 44447 | J26: 45
A27: C0026 | B27: Pacific Consumer Goods Plastics LLP | C27: India | D27: INR | E27: Healthcare | F27: BBB | G27: 39350000 | H27: 42390 | J27: 30
A28: C0027 | B28: Udaya Agri Products Ltd | C28: Bangladesh | D28: USD | E28: FMCG | F28: BBB | G28: 9250000 | H28: 42067 | J28: 60
A29: C0028 | B29: Rajdhani Consumer Goods Enterprises Pvt Ltd | C29: India | D29: INR | E29: Consumer Goods | F29: Unrated | G29: 58400000 | H29: 42189 | J29: 30
A30: C0029 | B30: Quartz Healthcare Polymers Pvt Ltd | C30: India | D30: INR | E30: Textiles | F30: Unrated | G30: 50800000 | H30: 43923 | J30: 90
A31: C0030 | B31: Cedar FMCG Industries Ltd | C31: India | D31: INR | E31: Agri Products | F31: BBB | G31: 42850000 | H31: 42401 | J31: 60
A32: C0031 | B32: Sahyadri Electricals Plastics LLP | C32: India | D32: INR | E32: Textiles | F32: AAA | G32: 94450000 | H32: 42134 | J32: 90
... A48: C0047 | B48: Aarav Industrial General Trading LLC | C48: UAE | D48: USD | E48: Agri Products | F48: AA | G48: 88650000 | H48: 44796 | J48: 90
A49: C0048 | B49: Zephyr Construction Industries Ltd | C49: India | D49: INR | E49: Healthcare | F49: B | G49: 0 | H49: 42249 | I49: Invalid limit | J49: 45
A50: C0049 | B50: Meridian Packaging Enterprises Pvt Ltd | C50: India | D50: INR | E50: Industrial | F50: AAA | G50: 218650000 | H50: 44130 | J50: 30
A51: C0050 | B51: Aarav Agri Products Plastics LLP | C51: India | D51: INR | E51: Auto Components | F51: A | G51: 202900000 | H51: 43674 | J51: 60
A52: C0051 | B52: Harbor Auto Components S.p.A. | C52: Italy | D52: EUR | E52: Textiles | F52: A | G52: 48950000 | H52: 44873 | J52: 60
A53: C0052 | B53: Unity Construction Plastics LLP | C53: India | D53: INR | E53: Packaging | F53: Unrated | G53: 102450000 | H53: 44012 | J53: 30
A54: C0053 | B54: Everest Healthcare GmbH | C54: Germany | D54: EUR | E54: Construction | F54: A | G54: 43150000 | H54: 44514 | J54: 60
A55: C0054 | B55: Ganga Auto Components GmbH | C55: Germany | D55: EUR | E55: FMCG | F55: A | G55: 95300000 | H55: 44259 | J55: 60
A56: C0055 | B56: Indus Industrial Industries Ltd | C56: India | D56: INR | E56: FMCG | F56: A | G56: 60000000 | H56: 43166 | J56: 45
A57: C0056 | B57: Yamuna Healthcare Industries Ltd | C57: India | D57: INR | E57: Construction | F57: BBB | G57: 52350000 | H57: 42477 | J57: 60
A58: C0057 | B58: Yamuna Industrial Industries Ltd | C58: India | D58: INR | E58: Industrial | F58: AA | G58: -5000000 | H58: 44474 | I58: Invalid limit | J58: 30
A59: C0058 | B59: Vista Textiles Enterprises Pvt Ltd | C59: India | D59: INR | E59: Packaging | F59: BBB | G59: 29800000 | H59: 44688 | J59: 30
A60: C0059 | B60: Harbor Packaging Polymers Pvt Ltd | C60: India | D60: INR | E60: Consumer Goods | F60: A | G60: 86550000 | H60: 43377 | J60: 30
A61: C0060 | B61: Quantum Electricals Polymers Pvt Ltd | C61: India | D61: INR | E61: Auto Components | F61: A | G61: 139200000 | H61: 42594 | J61: 45
A62: C0061 | B62: Delta Auto Components Plastics LLP | C62: India | D62: INR | E62: Electricals | F62: AA | G62: 53200000 | H62: 42816 | J62: 90
A63: C0062 | B63: Northstar Textiles Co. Ltd | C63: Vietnam | D63: USD | E63: FMCG | F63: BBB | G63: 19550000 | H63: 43431 | J63: 60
A64: C0063 | B64: Baltic Healthcare Plastics LLP | C64: India | D64: INR | E64: Healthcare | F64: A | G64: 67750000 | H64: 43482 | J64: 60
A65: C0064 | B65: Keystone Agri Products Co. Ltd | C65: Vietnam | D65: USD | E65: Textiles | F65: AA | G65: 41600000 | H65: 44241 | J65: 90
A66: C0065 | B66: Vertex Auto Components Industries Ltd | C66: India | D66: INR | E66: Electricals | F66: AAA | G66: 106900000 | H66: 43310 | J66: 30
A67: C0066 | B67: Juniper Consumer Goods Polymers Pvt Ltd | C67: India | D67: INR | E67: Construction | F67: BBB | G67: 55250000 | H67: 43398 | J67: 30
A68: C0067 | B68: Jupiter Construction GmbH | C68: Germany | D68: EUR | E68: FMCG | F68: BB | G68: 6750000 | H68: 43152 | J68: 45
A69: C0068 | B69: Redwood Auto Components Enterprises Pvt Ltd | C69: India | D69: INR | E69: FMCG | F69: BB | G69: 15050000 | H69: 42238 | J69: 60
A70: C0069 | B70: Kaveri Electricals Polymers Pvt Ltd | C70: India | D70: INR | E70: Packaging | F70: BB | G70: 46100000 | H70: 43376 | J70: 30
... A114: C0113 | B114: Bharat FMCG Industries Ltd | C114: India | D114: INR | E114: Agri Products | F114: AA | G114: 42200000 | H114: 44946 | J114: 90
A115: C0114 | B115: Horizon Auto Components Plastics LLP | C115: India | D115: INR | E115: Packaging | F115: B | G115: 0 | H115: 44265 | I115: Invalid limit | J115: 60
A116: C0115 | B116: Quantum Auto Components GmbH | C116: Germany | D116: EUR | E116: Consumer Goods | F116: B | G116: 17300000 | H116: 44753 | J116: 60
A117: C0116 | B117: Cedar Consumer Goods Enterprises Pvt Ltd | C117: India | D117: INR | E117: FMCG | F117: BB | G117: 23600000 | H117: 42445 | J117: 45
A118: C0117 | B118: Quantum Textiles Plastics LLP | C118: India | D118: INR | E118: Consumer Goods | F118: BBB | G118: 26550000 | H118: 42706 | J118: 45
A119: C0118 | B119: Pacific Auto Components Polymers Pvt Ltd | C119: India | D119: INR | E119: Construction | F119: BBB | G119: 37500000 | H119: 42773 | J119: 60
A120: C0119 | B120: Keystone Construction Polymers Pvt Ltd | C120: India | D120: INR | E120: Industrial | F120: AA | G120: 60450000 | H120: 44679 | J120: 60
A121: C0120 | B121: Unity Electricals LLC | C121: USA | D121: USD | E121: Healthcare | F121: BBB | G121: 10450000 | H121: 43449 | J121: 60
A122: C0121 | B122: Ganga FMCG Industries Ltd | C122: India | D122: INR | E122: Consumer Goods | F122: AA | G122: 60650000 | H122: 43078 | J122: 60
A123: C0122 | B123: Pioneer Electricals BV | C123: Netherlands | D123: EUR | E123: Consumer Goods | F123: BBB | G123: 13400000 | H123: 42713 | J123: 45
A124: C0123 | B124: Lotus Textiles Ltd | C124: Bangladesh | D124: USD | E124: Electricals | F124: Unrated | G124: 34950000 | H124: 43428 | J124: 60
A125: C0124 | B125: Jupiter Electricals Industries Ltd | C125: India | D125: INR | E125: Textiles | F125: BBB | G125: 17600000 | H125: 44106 | J125: 30
A126: C0125 | B126: Xenon Industrial Industries Ltd | C126: India | D126: INR | E126: Healthcare | F126: A | G126: 49100000 | H126: 42899 | J126: 45
A127: C0126 | B127: Ganga Healthcare BV | C127: Netherlands | D127: EUR | E127: Packaging | F127: BBB | G127: 17450000 | H127: 43945 | J127: 60
... A251: C0250 | B251: Lotus Consumer Goods Polymers Pvt Ltd | C251: India | D251: INR | E251: Construction | F251: A | G251: 37200000 | H251: 42466 | J251: 60

Sheet purchases
A1: purchase_id | B1: purchase_date | C1: bu_id | D1: currency | E1: quantity | F1: unit | G1: total_amount | H1: hedged_flag | I1: hedge_price | J1: material | K1: unit_price | L1: payment_date | M1: total_amount_INR | N1: days_to_pay_supplier
A2: PUR00005 | B2: 45019 | C2: BU03 | D2: USD | E2: 2153 | F2: bbl-eq | G2: 186083.79 | H2: N | J2: Crude-linked feedstock | K2: 86.43 | L2: 45049 | M2: =G2*IF(D2="INR",1,INDEX('rates'!$B$2:$B$522,MATCH(B2,'rates'!$A$2:$A$522,1))) -> 15303531 | N2: =IF(L2="","",L2-B2) -> 30
A3: PUR00012 | B3: 45023 | C3: BU04 | D3: INR | E3: 49318 | F3: kg | G3: 4419879.2 | H3: N | J3: Additives & packaging | K3: 89.62 | L3: 45053 | M3: =G3*IF(D3="INR",1,INDEX('rates'!$B$2:$B$522,MATCH(B3,'rates'!$A$2:$A$522,1))) -> 4419879.2 | N3: =IF(L3="","",L3-B3) -> 30
A4: PUR00013 | B4: 45023 | C4: BU04 | D4: USD | E4: 383 | F4: bbl-eq | G4: 32344.35 | H4: Y | I4: 86.03 | J4: Crude-linked feedstock | K4: 84.45 | L4: 45053 | M4: =G4*IF(D4="INR",1,INDEX('rates'!$B$2:$B$522,MATCH(B4,'rates'!$A$2:$A$522,1))) -> 2647385 | N4: =IF(L4="","",L4-B4) -> 30
A5: PUR00016 | B5: 45023 | C5: BU03 | D5: USD | E5: 1349 | F5: bbl-eq | G5: 115056.21 | H5: Y | I5: 86.03 | J5: Crude-linked feedstock | K5: 85.29 | L5: 45053 | M5: =G5*IF(D5="INR",1,INDEX('rates'!$B$2:$B$522,MATCH(B5,'rates'!$A$2:$A$522,1))) -> 9417350.8 | N5: =IF(L5="","",L5-B5) -> 30
A6: PUR00022 | B6: 45028 | C6: BU02 | D6: INR | E6: 29927 | F6: kg | G6: 2663802.3 | H6: N | J6: Additives & packaging | K6: 89.01 | L6: 45058 | M6: =G6*IF(D6="INR",1,INDEX('rates'!$B$2:$B$522,MATCH(B6,'rates'!$A$2:$A$522,1))) -> 2663802.3 | N6: =IF(L6="","",L6-B6) -> 30
A7: PUR00025 | B7: 45030 | C7: BU01 | D7: USD | E7: 429 | F7: bbl-eq | G7: 38361.18 | H7: N | J7: Crude-linked feedstock | K7: 89.42 | L7: 45060 | M7: =G7*IF(D7="INR",1,INDEX('rates'!$B$2:$B$522,MATCH(B7,'rates'!$A$2:$A$522,1))) -> 3141013.4 | N7: =IF(L7="","",L7-B7) -> 30
A8: PUR00029 | B8: 45033 | C8: BU05 | D8: USD | E8: 921 | F8: bbl-eq | G8: 79150.74 | H8: N | J8: Crude-linked feedstock | K8: 85.94 | L8: 45063 | M8: =G8*IF(D8="INR",1,INDEX('rates'!$B$2:$B$522,MATCH(B8,'rates'!$A$2:$A$522,1))) -> 6488777.7 | N8: =IF(L8="","",L8-B8) -> 30
A9: PUR00002 | B9: 45019 | C9: BU01 | D9: USD | E9: 1019 | F9: bbl-eq | G9: 88163.88 | H9: Y | I9: 86.03 | J9: Crude-linked feedstock | K9: 86.52 | L9: 45064 | M9: =G9*IF(D9="INR",1,INDEX('rates'!$B$2:$B$522,MATCH(B9,'rates'!$A$2:$A$522,1))) -> 7250597.5 | N9: =IF(L9="","",L9-B9) -> 45
A10: PUR00031 | B10: 45034 | C10: BU04 | D10: USD | E10: 1868 | F10: bbl-eq | G10: 160591.96 | H10: N | J10: Crude-linked feedstock | K10: 85.97 | L10: 45064 | M10: =G10*IF(D10="INR",1,INDEX('rates'!$B$2:$B$522,MATCH(B10,'rates'!$A$2:$A$522,1))) -> 13181388 | N10: =IF(L10="","",L10-B10) -> 30
A11: PUR00006 | B11: 45020 | C11: BU02 | D11: USD | E11: 1819 | F11: bbl-eq | G11: 152832.38 | H11: N | J11: Crude-linked feedstock | K11: 84.02 | L11: 45065 | M11: =G11*IF(D11="INR",1,INDEX('rates'!$B$2:$B$522,MATCH(B11,'rates'!$A$2:$A$522,1))) -> 12582690 | N11: =IF(L11="","",L11-B11) -> 45
A12: PUR00034 | B12: 45035 | C12: BU02 | D12: USD | E12: 689 | F12: bbl-eq | G12: 58220.5 | H12: Y | J12: Crude-linked feedstock | K12: 84.5 | L12: 45065 | M12: =G12*IF(D12="INR",1,INDEX('rates'!$B$2:$B$522,MATCH(B12,'rates'!$A$2:$A$522,1))) -> 4784560.7 | N12: =IF(L12="","",L12-B12) -> 30
A13: PUR00036 | B13: 45035 | C13: BU03 | D13: USD | E13: 1073 | F13: bbl-eq | G13: 90475.36 | H13: Y | I13: 86.03 | J13: Crude-linked feedstock | K13: 84.32 | L13: 45065 | M13: =G13*IF(D13="INR",1,INDEX('rates'!$B$2:$B$522,MATCH(B13,'rates'!$A$2:$A$522,1))) -> 7435265.1 | N13: =IF(L13="","",L13-B13) -> 30
A14: PUR00008 | B14: 45021 | C14: BU05 | D14: USD | E14: 877 | F14: bbl-eq | G14: 76035.9 | H14: Y | I14: 86.03 | J14: Crude-linked feedstock | K14: 86.7 | L14: 45066 | M14: =G14*IF(D14="INR",1,INDEX('rates'!$B$2:$B$522,MATCH(B14,'rates'!$A$2:$A$522,1))) -> 6226579.9 | N14: =IF(L14="","",L14-B14) -> 45
A15: PUR00009 | B15: 45022 | C15: BU04 | D15: USD | E15: 457 | F15: bbl-eq | G15: 38991.24 | H15: Y | I15: 86.03 | J15: Crude-linked feedstock | K15: 85.32 | L15: 45067 | M15: =G15*IF(D15="INR",1,INDEX('rates'!$B$2:$B$522,MATCH(B15,'rates'!$A$2:$A$522,1))) -> 3191822.9 | N15: =IF(L15="","",L15-B15) -> 45
A16: PUR00041 | B16: 45037 | C16: BU03 | D16: USD | E16: 1361 | F16: bbl-eq | G16: 112704.41 | H16: Y | I16: 86.03 | J16: Crude-linked feedstock | K16: 82.81 | L16: 45067 | M16: =G16*IF(D16="INR",1,INDEX('rates'!$B$2:$B$522,MATCH(B16,'rates'!$A$2:$A$522,1))) -> 9248523.9 | N16: =IF(L16="","",L16-B16) -> 30
A17: PUR00042 | B17: 45037 | C17: BU05 | D17: USD | E17: 676 | F17: bbl-eq | G17: 55911.96 | H17: N | J17: Crude-linked feedstock | K17: 82.71 | L17: 45067 | M17: =G17*IF(D17="INR",1,INDEX('rates'!$B$2:$B$522,MATCH(B17,'rates'!$A$2:$A$522,1))) -> 4588135.4 | N17: =IF(L17="","",L17-B17) -> 30
A18: PUR00046 | B18: 45037 | C18: BU03 | D18: USD | E18: 421 | F18: bbl-eq | G18: 34623.04 | H18: Y | I18: 86.03 | J18: Crude-linked feedstock | K18: 82.24 | L18: 45067 | M18: =G18*IF(D18="INR",1,INDEX('rates'!$B$2:$B$522,MATCH(B18,'rates'!$A$2:$A$522,1))) -> 2841166.7 | N18: =IF(L18="","",L18-B18) -> 30
A19: PUR00010 | B19: 45023 | C19: BU02 | D19: INR | E19: 59370 | F19: kg | G19: 5079697.2 | H19: N | J19: Additives & packaging | K19: 85.56 | L19: 45068 | M19: =G19*IF(D19="INR",1,INDEX('rates'!$B$2:$B$522,MATCH(B19,'rates'!$A$2:$A$522,1))) -> 5079697.2 | N19: =IF(L19="","",L19-B19) -> 45
A20: PUR00014 | B20: 45023 | C20: BU01 | D20: USD | E20: 917 | F20: bbl-eq | G20: 79513.07 | H20: N | J20: Crude-linked feedstock | K20: 86.71 | L20: 45068 | M20: =G20*IF(D20="INR",1,INDEX('rates'!$B$2:$B$522,MATCH(B20,'rates'!$A$2:$A$522,1))) -> 6508144.8 | N20: =IF(L20="","",L20-B20) -> 45
A21: PUR00047 | B21: 45040 | C21: BU05 | D21: USD | E21: 637 | F21: bbl-eq | G21: 53304.16 | H21: Y | I21: 86.03 | J21: Crude-linked feedstock | K21: 83.68 | L21: 45070 | M21: =G21*IF(D21="INR",1,INDEX('rates'!$B$2:$B$522,MATCH(B21,'rates'!$A$2:$A$522,1))) -> 4365610.7 | N21: =IF(L21="","",L21-B21) -> 30
A22: PUR00049 | B22: 45040 | C22: BU04 | D22: USD | E22: 712 | F22: bbl-eq | G22: 59644.24 | H22: N | J22: Crude-linked feedstock | K22: 83.77 | L22: 45070 | M22: =G22*IF(D22="INR",1,INDEX('rates'!$B$2:$B$522,MATCH(B22,'rates'!$A$2:$A$522,1))) -> 4884863.3 | N22: =IF(L22="","",L22-B22) -> 30
A23: PUR00050 | B23: 45042 | C23: BU02 | D23: USD | E23: 1545 | F23: bbl-eq | G23: 123182.85 | H23: N | J23: Crude-linked feedstock | K23: 79.73 | L23: 45072 | M23: =G23*IF(D23="INR",1,INDEX('rates'!$B$2:$B$522,MATCH(B23,'rates'!$A$2:$A$522,1))) -> 10068966 | N23: =IF(L23="","",L23-B23) -> 30
A24: PUR00051 | B24: 45042 | C24: BU04 | D24: USD | E24: 1129 | F24: bbl-eq | G24: 88457.15 | H24: N | J24: Crude-linked feedstock | K24: 78.35 | L24: 45072 | M24: =G24*IF(D24="INR",1,INDEX('rates'!$B$2:$B$522,MATCH(B24,'rates'!$A$2:$A$522,1))) -> 7230487.4 | N24: =IF(L24="","",L24-B24) -> 30
A25: PUR00021 | B25: 45028 | C25: BU02 | D25: USD | E25: 565 | F25: bbl-eq | G25: 50177.65 | H25: N | J25: Crude-linked feedstock | K25: 88.81 | L25: 45073 | M25: =G25*IF(D25="INR",1,INDEX('rates'!$B$2:$B$522,MATCH(B25,'rates'!$A$2:$A$522,1))) -> 4113563.7 | N25: =IF(L25="","",L25-B25) -> 45
A26: PUR00055 | B26: 45043 | C26: BU04 | D26: INR | E26: 125862 | F26: kg | G26: 10359701 | H26: N | J26: Additives & packaging | K26: 82.31 | L26: 45073 | M26: =G26*IF(D26="INR",1,INDEX('rates'!$B$2:$B$522,MATCH(B26,'rates'!$A$2:$A$522,1))) -> 10359701 | N26: =IF(L26="","",L26-B26) -> 30
A27: PUR00023 | B27: 45029 | C27: BU01 | D27: INR | E27: 34331 | F27: kg | G27: 3524420.5 | H27: N | J27: Additives & packaging | K27: 102.66 | L27: 45074 | M27: =G27*IF(D27="INR",1,INDEX('rates'!$B$2:$B$522,MATCH(B27,'rates'!$A$2:$A$522,1))) -> 3524420.5 | N27: =IF(L27="","",L27-B27) -> 45
A28: PUR00028 | B28: 45033 | C28: BU01 | D28: USD | E28: 1990 | F28: bbl-eq | G28: 167279.4 | H28: Y | I28: 86.03 | J28: Crude-linked feedstock | K28: 84.06 | L28: 45078 | M28: =G28*IF(D28="INR",1,INDEX('rates'!$B$2:$B$522,MATCH(B28,'rates'!$A$2:$A$522,1))) -> 13713565 | N28: =IF(L28="","",L28-B28) -> 45
A29: PUR00030 | B29: 45033 | C29: BU02 | D29: USD | E29: 371 | F29: bbl-eq | G29: 31449.67 | H29: Y | I29: 86.03 | J29: Crude-linked feedstock | K29: 84.77 | L29: 45078 | M29: =G29*IF(D29="INR",1,INDEX('rates'!$B$2:$B$522,MATCH(B29,'rates'!$A$2:$A$522,1))) -> 2578243.9 | N29: =IF(L29="","",L29-B29) -> 45
A30: PUR00001 | B30: 45019 | C30: BU03 | D30: USD | E30: 1609 | F30: bbl-eq | G30: 136604.1 | H30: N | J30: Crude-linked feedstock | K30: 84.9 | L30: 45079 | M30: =G30*IF(D30="INR",1,INDEX('rates'!$B$2:$B$522,MATCH(B30,'rates'!$A$2:$A$522,1))) -> 11234321 | N30: =IF(L30="","",L30-B30) -> 60
A31: PUR00003 | B31: 45019 | C31: BU04 | D31: USD | E31: 921 | F31: bbl-eq | G31: 78809.97 | H31: Y | I31: 86.03 | J31: Crude-linked feedstock | K31: 85.57 | L31: 45079 | M31: =G31*IF(D31="INR",1,INDEX('rates'!$B$2:$B$522,MATCH(B31,'rates'!$A$2:$A$522,1))) -> 6481331.9 | N31: =IF(L31="","",L31-B31) -> 60
A32: PUR00004 | B32: 45019 | C32: BU05 | D32: USD | E32: 1527 | F32: bbl-eq | G32: 130024.05 | H32: Y | I32: 86.03 | J32: Crude-linked feedstock | K32: 85.15 | L32: 45079 | M32: =G32*IF(D32="INR",1,INDEX('rates'!$B$2:$B$522,MATCH(B32,'rates'!$A$2:$A$522,1))) -> 10693178 | N32: =IF(L32="","",L32-B32) -> 60
A33: PUR00032 | B33: 45034 | C33: BU04 | D33: INR | E33: 36226 | F33: kg | G33: 3095874 | H33: N | J33: Additives & packaging | K33: 85.46 | L33: 45079 | M33: =G33*IF(D33="INR",1,INDEX('rates'!$B$2:$B$522,MATCH(B33,'rates'!$A$2:$A$522,1))) -> 3095874 | N33: =IF(L33="","",L33-B33) -> 45
A34: PUR00064 | B34: 45049 | C34: BU04 | D34: USD | E34: 2326 | F34: bbl-eq | G34: 168053.5 | H34: Y | I34: 86.03 | J34: Crude-linked feedstock | K34: 72.25 | L34: 45079 | M34: =G34*IF(D34="INR",1,INDEX('rates'!$B$2:$B$522,MATCH(B34,'rates'!$A$2:$A$522,1))) -> 13751818 | N34: =IF(L34="","",L34-B34) -> 30
A35: PUR00033 | B35: 45035 | C35: BU02 | D35: INR | E35: 109772 | F35: kg | G35: 9027649.3 | H35: N | J35: Additives & packaging | K35: 82.24 | L35: 45080 | M35: =G35*IF(D35="INR",1,INDEX('rates'!$B$2:$B$522,MATCH(B35,'rates'!$A$2:$A$522,1))) -> 9027649.3 | N35: =IF(L35="","",L35-B35) -> 45
A36: PUR00007 | B36: 45021 | C36: BU03 | D36: INR | E36: 45536 | F36: kg | G36: 3685228.5 | H36: N | J36: Additives & packaging | K36: 80.93 | L36: 45081 | M36: =G36*IF(D36="INR",1,INDEX('rates'!$B$2:$B$522,MATCH(B36,'rates'!$A$2:$A$522,1))) -> 3685228.5 | N36: =IF(L36="","",L36-B36) -> 60
A37: PUR00067 | B37: 45051 | C37: BU05 | D37: USD | E37: 695 | F37: bbl-eq | G37: 53049.35 | H37: Y | I37: 86.03 | J37: Crude-linked feedstock | K37: 76.33 | L37: 45081 | M37: =G37*IF(D37="INR",1,INDEX('rates'!$B$2:$B$522,MATCH(B37,'rates'!$A$2:$A$522,1))) -> 4339967.3 | N37: =IF(L37="","",L37-B37) -> 30
A38: PUR00037 | B38: 45037 | C38: BU02 | D38: USD | E38: 2428 | F38: bbl-eq | G38: 201014.12 | H38: N | J38: Crude-linked feedstock | K38: 82.79 | L38: 45082 | M38: =G38*IF(D38="INR",1,INDEX('rates'!$B$2:$B$522,MATCH(B38,'rates'!$A$2:$A$522,1))) -> 16495219 | N38: =IF(L38="","",L38-B38) -> 45
A39: PUR00039 | B39: 45037 | C39: BU05 | D39: INR | E39: 107990 | F39: kg | G39: 9223425.9 | H39: N | J39: Additives & packaging | K39: 85.41 | L39: 45082 | M39: =G39*IF(D39="INR",1,INDEX('rates'!$B$2:$B$522,MATCH(B39,'rates'!$A$2:$A$522,1))) -> 9223425.9 | N39: =IF(L39="","",L39-B39) -> 45
A40: PUR00043 | B40: 45037 | C40: BU01 | D40: USD | E40: 1796 | F40: bbl-eq | G40: 147505.48 | H40: N | J40: Crude-linked feedstock | K40: 82.13 | L40: 45082 | M40: =G40*IF(D40="INR",1,INDEX('rates'!$B$2:$B$522,MATCH(B40,'rates'!$A$2:$A$522,1))) -> 12104300 | N40: =IF(L40="","",L40-B40) -> 45
A41: PUR00044 | B41: 45037 | C41: BU02 | D41: USD | E41: 1694 | F41: bbl-eq | G41: 138061 | H41: N | J41: Crude-linked feedstock | K41: 81.5 | L41: 45082 | M41: =G41*IF(D41="INR",1,INDEX('rates'!$B$2:$B$522,MATCH(B41,'rates'!$A$2:$A$522,1))) -> 11329286 | N41: =IF(L41="","",L41-B41) -> 45
A42: PUR00011 | B42: 45023 | C42: BU02 | D42: USD | E42: 987 | F42: bbl-eq | G42: 84931.35 | H42: N | J42: Crude-linked feedstock | K42: 86.05 | L42: 45083 | M42: =G42*IF(D42="INR",1,INDEX('rates'!$B$2:$B$522,MATCH(B42,'rates'!$A$2:$A$522,1))) -> 6951631 | N42: =IF(L42="","",L42-B42) -> 60
A43: PUR00015 | B43: 45023 | C43: BU05 | D43: USD | E43: 2012 | F43: bbl-eq | G43: 167398.4 | H43: N | J43: Crude-linked feedstock | K43: 83.2 | L43: 45083 | M43: =G43*IF(D43="INR",1,INDEX('rates'!$B$2:$B$522,MATCH(B43,'rates'!$A$2:$A$522,1))) -> 13701559 | N43: =IF(L43="","",L43-B43) -> 60
A44: PUR00017 | B44: 45023 | C44: BU05 | D44: USD | E44: 1475 | F44: bbl-eq | G44: 129932.75 | H44: Y | I44: 86.03 | J44: Crude-linked feedstock | K44: 88.09 | L44: 45083 | M44: =G44*IF(D44="INR",1,INDEX('rates'!$B$2:$B$522,MATCH(B44,'rates'!$A$2:$A$522,1))) -> 10634996 | N44: =IF(L44="","",L44-B44) -> 60
A45: PUR00070 | B45: 45054 | C45: BU03 | D45: USD | E45: 205 | F45: bbl-eq | G45: 15832.15 | H45: N | J45: Crude-linked feedstock | K45: 77.23 | L45: 45084 | M45: =G45*IF(D45="INR",1,INDEX('rates'!$B$2:$B$522,MATCH(B45,'rates'!$A$2:$A$522,1))) -> 1294753.2 | N45: =IF(L45="","",L45-B45) -> 30
A46: PUR00072 | B46: 45054 | C46: BU02 | D46: USD | E46: 717 | F46: bbl-eq | G46: 56126.76 | H46: N | J46: Crude-linked feedstock | K46: 78.28 | L46: 45084 | M46: =G46*IF(D46="INR",1,INDEX('rates'!$B$2:$B$522,MATCH(B46,'rates'!$A$2:$A$522,1))) -> 4590046.4 | N46: =IF(L46="","",L46-B46) -> 30
A47: PUR00048 | B47: 45040 | C47: BU05 | D47: USD | E47: 562 | F47: bbl-eq | G47: 45600.68 | H47: N | J47: Crude-linked feedstock | K47: 81.14 | L47: 45085 | M47: =G47*IF(D47="INR",1,INDEX('rates'!$B$2:$B$522,MATCH(B47,'rates'!$A$2:$A$522,1))) -> 3734695.7 | N47: =IF(L47="","",L47-B47) -> 45
A48: PUR00073 | B48: 45055 | C48: BU04 | D48: USD | E48: 1925 | F48: bbl-eq | G48: 150265.5 | H48: N | J48: Crude-linked feedstock | K48: 78.06 | L48: 45085 | M48: =G48*IF(D48="INR",1,INDEX('rates'!$B$2:$B$522,MATCH(B48,'rates'!$A$2:$A$522,1))) -> 12327782 | N48: =IF(L48="","",L48-B48) -> 30
A49: PUR00018 | B49: 45026 | C49: BU01 | D49: USD | E49: 340 | F49: bbl-eq | G49: 28903.4 | H49: Y | I49: 86.03 | J49: Crude-linked feedstock | K49: 85.01 | L49: 45086 | M49: =G49*IF(D49="INR",1,INDEX('rates'!$B$2:$B$522,MATCH(B49,'rates'!$A$2:$A$522,1))) -> 2370367.8 | N49: =IF(L49="","",L49-B49) -> 60
A50: PUR00076 | B50: 45056 | C50: BU02 | D50: USD | E50: 2176 | F50: bbl-eq | G50: 170010.88 | H50: N | J50: Crude-linked feedstock | K50: 78.13 | L50: 45086 | M50: =G50*IF(D50="INR",1,INDEX('rates'!$B$2:$B$522,MATCH(B50,'rates'!$A$2:$A$522,1))) -> 13930692 | N50: =IF(L50="","",L50-B50) -> 30
A51: PUR00019 | B51: 45027 | C51: BU03 | D51: USD | E51: 1132 | F51: bbl-eq | G51: 97702.92 | H51: N | J51: Crude-linked feedstock | K51: 86.31 | L51: 45087 | M51: =G51*IF(D51="INR",1,INDEX('rates'!$B$2:$B$522,MATCH(B51,'rates'!$A$2:$A$522,1))) -> 8015547.6 | N51: =IF(L51="","",L51-B51) -> 60
A52: PUR00020 | B52: 45027 | C52: BU02 | D52: USD | E52: 1285 | F52: bbl-eq | G52: 112077.7 | H52: Y | I52: 86.03 | J52: Crude-linked feedstock | K52: 87.22 | L52: 45087 | M52: =G52*IF(D52="INR",1,INDEX('rates'!$B$2:$B$522,MATCH(B52,'rates'!$A$2:$A$522,1))) -> 9194854.5 | N52: =IF(L52="","",L52-B52) -> 60
A53: PUR00077 | B53: 45057 | C53: BU01 | D53: INR | E53: 64077 | F53: kg | G53: 5542019.7 | H53: N | J53: Additives & packaging | K53: 86.49 | L53: 45087 | M53: =G53*IF(D53="INR",1,INDEX('rates'!$B$2:$B$522,MATCH(B53,'rates'!$A$2:$A$522,1))) -> 5542019.7 | N53: =IF(L53="","",L53-B53) -> 30
A54: PUR00079 | B54: 45057 | C54: BU03 | D54: USD | E54: 716 | F54: bbl-eq | G54: 54544.88 | H54: Y | I54: 86.03 | J54: Crude-linked feedstock | K54: 76.18 | L54: 45087 | M54: =G54*IF(D54="INR",1,INDEX('rates'!$B$2:$B$522,MATCH(B54,'rates'!$A$2:$A$522,1))) -> 4479771 | N54: =IF(L54="","",L54-B54) -> 30
A55: PUR00054 | B55: 45043 | C55: BU02 | D55: USD | E55: 1278 | F55: bbl-eq | G55: 100246.32 | H55: N | J55: Crude-linked feedstock | K55: 78.44 | L55: 45088 | M55: =G55*IF(D55="INR",1,INDEX('rates'!$B$2:$B$522,MATCH(B55,'rates'!$A$2:$A$522,1))) -> 8204158.8 | N55: =IF(L55="","",L55-B55) -> 45
A56: PUR00057 | B56: 45043 | C56: BU03 | D56: USD | E56: 633 | F56: bbl-eq | G56: 49247.4 | H56: N | J56: Crude-linked feedstock | K56: 77.8 | L56: 45088 | M56: =G56*IF(D56="INR",1,INDEX('rates'!$B$2:$B$522,MATCH(B56,'rates'!$A$2:$A$522,1))) -> 4030407.2 | N56: =IF(L56="","",L56-B56) -> 45
A57: PUR00080 | B57: 45058 | C57: BU01 | D57: INR | E57: 71760 | F57: kg | G57: 4587616.8 | H57: N | J57: Additives & packaging | K57: 63.93 | L57: 45088 | M57: =G57*IF(D57="INR",1,INDEX('rates'!$B$2:$B$522,MATCH(B57,'rates'!$A$2:$A$522,1))) -> 4587616.8 | N57: =IF(L57="","",L57-B57) -> 30
A58: PUR00086 | B58: 45058 | C58: BU04 | D58: USD | E58: 1287 | F58: bbl-eq | G58: 95945.85 | H58: N | J58: Crude-linked feedstock | K58: 74.55 | L58: 45088 | M58: =G58*IF(D58="INR",1,INDEX('rates'!$B$2:$B$522,MATCH(B58,'rates'!$A$2:$A$522,1))) -> 7883870.5 | N58: =IF(L58="","",L58-B58) -> 30
A59: PUR00087 | B59: 45058 | C59: BU03 | D59: USD | E59: 1059 | F59: bbl-eq | G59: 78980.22 | H59: N | J59: Crude-linked feedstock | K59: 74.58 | L59: 45088 | M59: =G59*IF(D59="INR",1,INDEX('rates'!$B$2:$B$522,MATCH(B59,'rates'!$A$2:$A$522,1))) -> 6489804.7 | N59: =IF(L59="","",L59-B59) -> 30
A60: PUR00058 | B60: 45044 | C60: BU01 | D60: USD | E60: 691 | F60: bbl-eq | G60: 57373.73 | H60: Y | I60: 86.03 | J60: Crude-linked feedstock | K60: 83.03 | L60: 45089 | M60: =G60*IF(D60="INR",1,INDEX('rates'!$B$2:$B$522,MATCH(B60,'rates'!$A$2:$A$522,1))) -> 4695466.1 | N60: =IF(L60="","",L60-B60) -> 45
A61: PUR00024 | B61: 45030 | C61: BU01 | D61: INR | E61: 51152 | F61: kg | G61: 4632325.1 | H61: N | J61: Additives & packaging | K61: 90.56 | L61: 45090 | M61: =G61*IF(D61="INR",1,INDEX('rates'!$B$2:$B$522,MATCH(B61,'rates'!$A$2:$A$522,1))) -> 4632325.1 | N61: =IF(L61="","",L61-B61) -> 60
A62: PUR00026 | B62: 45030 | C62: BU05 | D62: USD | E62: 509 | F62: bbl-eq | G62: 43768.91 | H62: Y | I62: 86.03 | J62: Crude-linked feedstock | K62: 85.99 | L62: 45090 | M62: =G62*IF(D62="INR",1,INDEX('rates'!$B$2:$B$522,MATCH(B62,'rates'!$A$2:$A$522,1))) -> 3583798.4 | N62: =IF(L62="","",L62-B62) -> 60
A63: PUR00027 | B63: 45030 | C63: BU02 | D63: INR | E63: 106539 | F63: kg | G63: 8428300.3 | H63: N | J63: Additives & packaging | K63: 79.11 | L63: 45090 | M63: =G63*IF(D63="INR",1,INDEX('rates'!$B$2:$B$522,MATCH(B63,'rates'!$A$2:$A$522,1))) -> 8428300.3 | N63: =IF(L63="","",L63-B63) -> 60
A64: PUR00090 | B64: 45062 | C64: BU02 | D64: INR | E64: 31616 | F64: kg | G64: 2955147.5 | H64: N | J64: Additives & packaging | K64: 93.47 | L64: 45092 | M64: =G64*IF(D64="INR",1,INDEX('rates'!$B$2:$B$522,MATCH(B64,'rates'!$A$2:$A$522,1))) -> 2955147.5 | N64: =IF(L64="","",L64-B64) -> 30
A65: PUR00091 | B65: 45062 | C65: BU01 | D65: USD | E65: 896 | F65: bbl-eq | G65: 67854.08 | H65: Y | I65: 86.03 | J65: Crude-linked feedstock | K65: 75.73 | L65: 45092 | M65: =G65*IF(D65="INR",1,INDEX('rates'!$B$2:$B$522,MATCH(B65,'rates'!$A$2:$A$522,1))) -> 5581676.6 | N65: =IF(L65="","",L65-B65) -> 30
A66: PUR00092 | B66: 45062 | C66: BU02 | D66: USD | E66: 694 | F66: bbl-eq | G66: 49850.02 | H66: N | J66: Crude-linked feedstock | K66: 71.83 | L66: 45092 | M66: =G66*IF(D66="INR",1,INDEX('rates'!$B$2:$B$522,MATCH(B66,'rates'!$A$2:$A$522,1))) -> 4100662.6 | N66: =IF(L66="","",L66-B66) -> 30
A67: PUR00065 | B67: 45049 | C67: BU01 | D67: USD | E67: 382 | F67: bbl-eq | G67: 28306.2 | H67: Y | I67: 86.03 | J67: Crude-linked feedstock | K67: 74.1 | L67: 45094 | M67: =G67*IF(D67="INR",1,INDEX('rates'!$B$2:$B$522,MATCH(B67,'rates'!$A$2:$A$522,1))) -> 2316296.3 | N67: =IF(L67="","",L67-B67) -> 45
A68: PUR00093 | B68: 45064 | C68: BU04 | D68: USD | E68: 616 | F68: bbl-eq | G68: 46674.32 | H68: Y | I68: 86.03 | J68: Crude-linked feedstock | K68: 75.77 | L68: 45094 | M68: =G68*IF(D68="INR",1,INDEX('rates'!$B$2:$B$522,MATCH(B68,'rates'!$A$2:$A$522,1))) -> 3863233.5 | N68: =IF(L68="","",L68-B68) -> 30
A69: PUR00035 | B69: 45035 | C69: BU05 | D69: USD | E69: 313 | F69: bbl-eq | G69: 25766.16 | H69: N | J69: Crude-linked feedstock | K69: 82.32 | L69: 45095 | M69: =G69*IF(D69="INR",1,INDEX('rates'!$B$2:$B$522,MATCH(B69,'rates'!$A$2:$A$522,1))) -> 2117463 | N69: =IF(L69="","",L69-B69) -> 60
A70: PUR00094 | B70: 45065 | C70: BU01 | D70: USD | E70: 367 | F70: bbl-eq | G70: 26974.5 | H70: N | J70: Crude-linked feedstock | K70: 73.5 | L70: 45095 | M70: =G70*IF(D70="INR",1,INDEX('rates'!$B$2:$B$522,MATCH(B70,'rates'!$A$2:$A$522,1))) -> 2229442.4 | N70: =IF(L70="","",L70-B70) -> 30
A71: PUR00069 | B71: 45051 | C71: BU01 | D71: USD | E71: 1072 | F71: bbl-eq | G71: 81139.68 | H71: Y | I71: 86.03 | J71: Crude-linked feedstock | K71: 75.69 | L71: 45096 | M71: =G71*IF(D71="INR",1,INDEX('rates'!$B$2:$B$522,MATCH(B71,'rates'!$A$2:$A$522,1))) -> 6638037.2 | N71: =IF(L71="","",L71-B71) -> 45
A72: PUR00038 | B72: 45037 | C72: BU02 | D72: USD | E72: 1273 | F72: bbl-eq | G72: 105697.19 | H72: N | J72: Crude-linked feedstock | K72: 83.03 | L72: 45097 | M72: =G72*IF(D72="INR",1,INDEX('rates'!$B$2:$B$522,MATCH(B72,'rates'!$A$2:$A$522,1))) -> 8673511.4 | N72: =IF(L72="","",L72-B72) -> 60
A73: PUR00040 | B73: 45037 | C73: BU04 | D73: USD | E73: 658 | F73: bbl-eq | G73: 53778.34 | H73: Y | I73: 86.03 | J73: Crude-linked feedstock | K73: 81.73 | L73: 45097 | M73: =G73*IF(D73="INR",1,INDEX('rates'!$B$2:$B$522,MATCH(B73,'rates'!$A$2:$A$522,1))) -> 4413050.6 | N73: =IF(L73="","",L73-B73) -> 60
A74: PUR00045 | B74: 45037 | C74: BU04 | D74: USD | E74: 421 | F74: bbl-eq | G74: 33587.38 | H74: N | J74: Crude-linked feedstock | K74: 79.78 | L74: 45097 | M74: =G74*IF(D74="INR",1,INDEX('rates'!$B$2:$B$522,MATCH(B74,'rates'!$A$2:$A$522,1))) -> 2756180.4 | N74: =IF(L74="","",L74-B74) -> 60
A75: PUR00098 | B75: 45068 | C75: BU03 | D75: INR | E75: 37074 | F75: kg | G75: 3344074.8 | H75: N | J75: Additives & packaging | K75: 90.2 | L75: 45098 | M75: =G75*IF(D75="INR",1,INDEX('rates'!$B$2:$B$522,MATCH(B75,'rates'!$A$2:$A$522,1))) -> 3344074.8 | N75: =IF(L75="","",L75-B75) -> 30
A76: PUR00071 | B76: 45054 | C76: BU02 | D76: USD | E76: 1187 | F76: bbl-eq | G76: 91125.99 | H76: N | J76: Crude-linked feedstock | K76: 76.77 | L76: 45099 | M76: =G76*IF(D76="INR",1,INDEX('rates'!$B$2:$B$522,MATCH(B76,'rates'!$A$2:$A$522,1))) -> 7452283.5 | N76: =IF(L76="","",L76-B76) -> 45
A77: PUR00100 | B77: 45069 | C77: BU02 | D77: INR | E77: 44974 | F77: kg | G77: 2577909.7 | H77: N | J77: Additives & packaging | K77: 57.32 | L77: 45099 | M77: =G77*IF(D77="INR",1,INDEX('rates'!$B$2:$B$522,MATCH(B77,'rates'!$A$2:$A$522,1))) -> 2577909.7 | N77: =IF(L77="","",L77-B77) -> 30
A78: PUR00075 | B78: 45056 | C78: BU02 | D78: INR | E78: 83334 | F78: kg | G78: 7626727.7 | H78: N | J78: Additives & packaging | K78: 91.52 | L78: 45101 | M78: =G78*IF(D78="INR",1,INDEX('rates'!$B$2:$B$522,MATCH(B78,'rates'!$A$2:$A$522,1))) -> 7626727.7 | N78: =IF(L78="","",L78-B78) -> 45
A79: PUR00104 | B79: 45071 | C79: BU05 | D79: INR | E79: 66908 | F79: kg | G79: 4453396.5 | H79: N | J79: Additives & packaging | K79: 66.56 | L79: 45101 | M79: =G79*IF(D79="INR",1,INDEX('rates'!$B$2:$B$522,MATCH(B79,'rates'!$A$2:$A$522,1))) -> 4453396.5 | N79: =IF(L79="","",L79-B79) -> 30
A80: PUR00105 | B80: 45071 | C80: BU05 | D80: INR | E80: 69810 | F80: kg | G80: 5629478.4 | H80: N | J80: Additives & packaging | K80: 80.64 | L80: 45101 | M80: =G80*IF(D80="INR",1,INDEX('rates'!$B$2:$B$522,MATCH(B80,'rates'!$A$2:$A$522,1))) -> 5629478.4 | N80: =IF(L80="","",L80-B80) -> 30
A81: PUR00052 | B81: 45042 | C81: BU02 | D81: USD | E81: 1048 | F81: bbl-eq | G81: 84730.8 | H81: N | J81: Crude-linked feedstock | K81: 80.85 | L81: 45102 | M81: =G81*IF(D81="INR",1,INDEX('rates'!$B$2:$B$522,MATCH(B81,'rates'!$A$2:$A$522,1))) -> 6925895.6 | N81: =IF(L81="","",L81-B81) -> 60
A82: PUR00078 | B82: 45057 | C82: BU02 | D82: USD | E82: 759 | F82: bbl-eq | G82: 57372.81 | H82: Y | I82: 86.03 | J82: Crude-linked feedstock | K82: 75.59 | L82: 45102 | M82: =G82*IF(D82="INR",1,INDEX('rates'!$B$2:$B$522,MATCH(B82,'rates'!$A$2:$A$522,1))) -> 4712028.9 | N82: =IF(L82="","",L82-B82) -> 45
A83: PUR00106 | B83: 45072 | C83: BU01 | D83: USD | E83: 5334 | F83: bbl-eq | G83: 409277.82 | H83: Y | I83: 86.03 | J83: Crude-linked feedstock | K83: 76.73 | L83: 45102 | M83: =G83*IF(D83="INR",1,INDEX('rates'!$B$2:$B$522,MATCH(B83,'rates'!$A$2:$A$522,1))) -> 33798162 | N83: =IF(L83="","",L83-B83) -> 30
A84: PUR00109 | B84: 45072 | C84: BU05 | D84: INR | E84: 131867 | F84: kg | G84: 12305828 | H84: N | J84: Additives & packaging | K84: 93.32 | L84: 45102 | M84: =G84*IF(D84="INR",1,INDEX('rates'!$B$2:$B$522,MATCH(B84,'rates'!$A$2:$A$522,1))) -> 12305828 | N84: =IF(L84="","",L84-B84) -> 30
A85: PUR00110 | B85: 45072 | C85: BU01 | D85: USD | E85: 1839 | F85: bbl-eq | G85: 143846.58 | H85: N | J85: Crude-linked feedstock | K85: 78.22 | L85: 45102 | M85: =G85*IF(D85="INR",1,INDEX('rates'!$B$2:$B$522,MATCH(B85,'rates'!$A$2:$A$522,1))) -> 11878851 | N85: =IF(L85="","",L85-B85) -> 30
A86: PUR00111 | B86: 45072 | C86: BU02 | D86: USD | E86: 163 | F86: bbl-eq | G86: 12340.73 | H86: N | J86: Crude-linked feedstock | K86: 75.71 | L86: 45102 | M86: =G86*IF(D86="INR",1,INDEX('rates'!$B$2:$B$522,MATCH(B86,'rates'!$A$2:$A$522,1))) -> 1019097.5 | N86: =IF(L86="","",L86-B86) -> 30
A87: PUR00053 | B87: 45043 | C87: BU01 | D87: USD | E87: 666 | F87: bbl-eq | G87: 51801.48 | H87: N | J87: Crude-linked feedstock | K87: 77.78 | L87: 45103 | M87: =G87*IF(D87="INR",1,INDEX('rates'!$B$2:$B$522,MATCH(B87,'rates'!$A$2:$A$522,1))) -> 4239433.1 | N87: =IF(L87="","",L87-B87) -> 60
A88: PUR00056 | B88: 45043 | C88: BU02 | D88: USD | E88: 5682 | F88: bbl-eq | G88: 439048.14 | H88: Y | I88: 86.03 | J88: Crude-linked feedstock | K88: 77.27 | L88: 45103 | M88: =G88*IF(D88="INR",1,INDEX('rates'!$B$2:$B$522,MATCH(B88,'rates'!$A$2:$A$522,1))) -> 35931700 | N88: =IF(L88="","",L88-B88) -> 60
A89: PUR00081 | B89: 45058 | C89: BU01 | D89: USD | E89: 413 | F89: bbl-eq | G89: 31284.75 | H89: Y | I89: 86.03 | J89: Crude-linked feedstock | K89: 75.75 | L89: 45103 | M89: =G89*IF(D89="INR",1,INDEX('rates'!$B$2:$B$522,MATCH(B89,'rates'!$A$2:$A$522,1))) -> 2570667.9 | N89: =IF(L89="","",L89-B89) -> 45
A90: PUR00082 | B90: 45058 | C90: BU01 | D90: USD | E90: 192 | F90: bbl-eq | G90: 14238.72 | H90: Y | I90: 86.03 | J90: Crude-linked feedstock | K90: 74.16 | L90: 45103 | M90: =G90*IF(D90="INR",1,INDEX('rates'!$B$2:$B$522,MATCH(B90,'rates'!$A$2:$A$522,1))) -> 1169995.6 | N90: =IF(L90="","",L90-B90) -> 45
A91: PUR00083 | B91: 45058 | C91: BU01 | D91: INR | E91: 44366 | F91: kg | G91: 3674392.1 | H91: N | J91: Additives & packaging | K91: 82.82 | L91: 45103 | M91: =G91*IF(D91="INR",1,INDEX('rates'!$B$2:$B$522,MATCH(B91,'rates'!$A$2:$A$522,1))) -> 3674392.1 | N91: =IF(L91="","",L91-B91) -> 45
A92: PUR00085 | B92: 45058 | C92: BU01 | D92: INR | E92: 145396 | F92: kg | G92: 12153652 | H92: N | J92: Additives & packaging | K92: 83.59 | L92: 45103 | M92: =G92*IF(D92="INR",1,INDEX('rates'!$B$2:$B$522,MATCH(B92,'rates'!$A$2:$A$522,1))) -> 12153652 | N92: =IF(L92="","",L92-B92) -> 45
A93: PUR00059 | B93: 45044 | C93: BU01 | D93: USD | E93: 529 | F93: bbl-eq | G93: 43552.57 | H93: Y | I93: 86.03 | J93: Crude-linked feedstock | K93: 82.33 | L93: 45104 | M93: =G93*IF(D93="INR",1,INDEX('rates'!$B$2:$B$522,MATCH(B93,'rates'!$A$2:$A$522,1))) -> 3564342.3 | N93: =IF(L93="","",L93-B93) -> 60
A94: PUR00060 | B94: 45044 | C94: BU02 | D94: INR | E94: 60556 | F94: kg | G94: 5651085.9 | H94: N | J94: Additives & packaging | K94: 93.32 | L94: 45104 | M94: =G94*IF(D94="INR",1,INDEX('rates'!$B$2:$B$522,MATCH(B94,'rates'!$A$2:$A$522,1))) -> 5651085.9 | N94: =IF(L94="","",L94-B94) -> 60
A95: PUR00061 | B95: 45044 | C95: BU01 | D95: USD | E95: 1148 | F95: bbl-eq | G95: 93986.76 | H95: Y | I95: 86.03 | J95: Crude-linked feedstock | K95: 81.87 | L95: 45104 | M95: =G95*IF(D95="INR",1,INDEX('rates'!$B$2:$B$522,MATCH(B95,'rates'!$A$2:$A$522,1))) -> 7691876.4 | N95: =IF(L95="","",L95-B95) -> 60
A96: PUR00062 | B96: 45044 | C96: BU03 | D96: USD | E96: 396 | F96: bbl-eq | G96: 31810.68 | H96: Y | I96: 86.03 | J96: Crude-linked feedstock | K96: 80.33 | L96: 45104 | M96: =G96*IF(D96="INR",1,INDEX('rates'!$B$2:$B$522,MATCH(B96,'rates'!$A$2:$A$522,1))) -> 2603386.1 | N96: =IF(L96="","",L96-B96) -> 60
A97: PUR00063 | B97: 45044 | C97: BU01 | D97: USD | E97: 1010 | F97: bbl-eq | G97: 81961.5 | H97: Y | I97: 86.03 | J97: Crude-linked feedstock | K97: 81.15 | L97: 45104 | M97: =G97*IF(D97="INR",1,INDEX('rates'!$B$2:$B$522,MATCH(B97,'rates'!$A$2:$A$522,1))) -> 6707729.2 | N97: =IF(L97="","",L97-B97) -> 60
A98: PUR00113 | B98: 45075 | C98: BU02 | D98: USD | E98: 419 | F98: bbl-eq | G98: 32313.28 | H98: N | J98: Crude-linked feedstock | K98: 77.12 | L98: 45105 | M98: =G98*IF(D98="INR",1,INDEX('rates'!$B$2:$B$522,MATCH(B98,'rates'!$A$2:$A$522,1))) -> 2668430.7 | N98: =IF(L98="","",L98-B98) -> 30
A99: PUR00114 | B99: 45075 | C99: BU02 | D99: USD | E99: 666 | F99: bbl-eq | G99: 51015.6 | H99: Y | I99: 86.03 | J99: Crude-linked feedstock | K99: 76.6 | L99: 45105 | M99: =G99*IF(D99="INR",1,INDEX('rates'!$B$2:$B$522,MATCH(B99,'rates'!$A$2:$A$522,1))) -> 4212868.2 | N99: =IF(L99="","",L99-B99) -> 30
A100: PUR00115 | B100: 45075 | C100: BU01 | D100: USD | E100: 730 | F100: bbl-eq | G100: 55275.6 | H100: N | J100: Crude-linked feedstock | K100: 75.72 | L100: 45105 | M100: =G100*IF(D100="INR",1,INDEX('rates'!$B$2:$B$522,MATCH(B100,'rates'!$A$2:$A$522,1))) -> 4564659 | N100: =IF(L100="","",L100-B100) -> 30
...

Sheet market_prices
A1: price_id | B1: date | C1: asset | D1: asset_class | E1: price | F1: unit | G1: source | H1: carried_forward
A2: MP00522 | B2: 45019 | C2: EUR/INR | D2: FX | E2: 89.5676 | F2: INR per EUR | G2: Derived: FRED DEXUSEU x DEXINUS (Federal Reserve H.10) | H2: No
A3: MP00523 | B3: 45020 | C3: EUR/INR | D3: FX | E3: 90.1596 | F3: INR per EUR | G3: Derived: FRED DEXUSEU x DEXINUS (Federal Reserve H.10) | H3: No
A4: MP00524 | B4: 45021 | C4: EUR/INR | D4: FX | E4: 89.4075 | F4: INR per EUR | G4: Derived: FRED DEXUSEU x DEXINUS (Federal Reserve H.10) | H4: No
A5: MP00525 | B5: 45022 | C5: EUR/INR | D5: FX | E5: 89.4484 | F5: INR per EUR | G5: Derived: FRED DEXUSEU x DEXINUS (Federal Reserve H.10) | H5: No
A6: MP00526 | B6: 45023 | C6: EUR/INR | D6: FX | E6: 89.3229 | F6: INR per EUR | G6: Derived: FRED DEXUSEU x DEXINUS (Federal Reserve H.10) | H6: No
A7: MP00527 | B7: 45026 | C7: EUR/INR | D7: FX | E7: 88.8988 | F7: INR per EUR | G7: Derived: FRED DEXUSEU x DEXINUS (Federal Reserve H.10) | H7: No
A8: MP00528 | B8: 45027 | C8: EUR/INR | D8: FX | E8: 89.4728 | F8: INR per EUR | G8: Derived: FRED DEXUSEU x DEXINUS (Federal Reserve H.10) | H8: No
A9: MP00529 | B9: 45028 | C9: EUR/INR | D9: FX | E9: 90.0714 | F9: INR per EUR | G9: Derived: FRED DEXUSEU x DEXINUS (Federal Reserve H.10) | H9: No
A10: MP00530 | B10: 45029 | C10: EUR/INR | D10: FX | E10: 90.2559 | F10: INR per EUR | G10: Derived: FRED DEXUSEU x DEXINUS (Federal Reserve H.10) | H10: No
A11: MP00531 | B11: 45030 | C11: EUR/INR | D11: FX | E11: 89.9042 | F11: INR per EUR | G11: Derived: FRED DEXUSEU x DEXINUS (Federal Reserve H.10) | H11: No
A12: MP00532 | B12: 45033 | C12: EUR/INR | D12: FX | E12: 89.4812 | F12: INR per EUR | G12: Derived: FRED DEXUSEU x DEXINUS (Federal Reserve H.10) | H12: No
A13: MP00533 | B13: 45034 | C13: EUR/INR | D13: FX | E13: 89.9433 | F13: INR per EUR | G13: Derived: FRED DEXUSEU x DEXINUS (Federal Reserve H.10) | H13: No
... A1564: MP01563 | B1564: 45747 | C1564: WTI Crude | D1564: Commodity | E1564: 71.87 | F1564: USD per barrel | G1564: FRED DCOILWTICO (US EIA) | H1564: No

Sheet rates
A1: date | B1: USD/INR | C1: EUR/INR | D1: WTI Crude | E1: USD/INR return | F1: EUR/INR return | G1: WTI return
A2: 45019 | B2: =SUMIFS(market_prices!$E:$E,market_prices!$B:$B,$A2,market_prices!$C:$C,B$1) -> 82.24 | C2: =SUMIFS(market_prices!$E:$E,market_prices!$B:$B,$A2,market_prices!$C:$C,C$1) -> 89.5676 | D2: =SUMIFS(market_prices!$E:$E,market_prices!$B:$B,$A2,market_prices!$C:$C,D$1) -> 80.4
A3: 45020 | B3: =SUMIFS(market_prices!$E:$E,market_prices!$B:$B,$A3,market_prices!$C:$C,B$1) -> 82.33 | C3: =SUMIFS(market_prices!$E:$E,market_prices!$B:$B,$A3,market_prices!$C:$C,C$1) -> 90.1596 | D3: =SUMIFS(market_prices!$E:$E,market_prices!$B:$B,$A3,market_prices!$C:$C,D$1) -> 80.7 | E3: =B3/B2-1 -> 0.001094358 | F3: =rates[[#This Row],[EUR/INR]]/C2-1 -> 0.0066095329 | G3: =rates[[#This Row],[WTI Crude]]/D2-1 -> 0.0037313433
A4: 45021 | B4: =SUMIFS(market_prices!$E:$E,market_prices!$B:$B,$A4,market_prices!$C:$C,B$1) -> 81.89 | C4: =SUMIFS(market_prices!$E:$E,market_prices!$B:$B,$A4,market_prices!$C:$C,C$1) -> 89.4075 | D4: =SUMIFS(market_prices!$E:$E,market_prices!$B:$B,$A4,market_prices!$C:$C,D$1) -> 80.69 | E4: =B4/B3-1 -> -0.0053443459 | F4: =rates[[#This Row],[EUR/INR]]/C3-1 -> -0.0083418737 | G4: =rates[[#This Row],[WTI Crude]]/D3-1 -> -0.00012391574
A5: 45022 | B5: =SUMIFS(market_prices!$E:$E,market_prices!$B:$B,$A5,market_prices!$C:$C,B$1) -> 81.86 | C5: =SUMIFS(market_prices!$E:$E,market_prices!$B:$B,$A5,market_prices!$C:$C,C$1) -> 89.4484 | D5: =SUMIFS(market_prices!$E:$E,market_prices!$B:$B,$A5,market_prices!$C:$C,D$1) -> 80.7 | E5: =B5/B4-1 -> -0.0003663451 | F5: =rates[[#This Row],[EUR/INR]]/C4-1 -> 0.00045745603 | G5: =rates[[#This Row],[WTI Crude]]/D4-1 -> 0.00012393109
A6: 45023 | B6: =SUMIFS(market_prices!$E:$E,market_prices!$B:$B,$A6,market_prices!$C:$C,B$1) -> 81.85 | C6: =SUMIFS(market_prices!$E:$E,market_prices!$B:$B,$A6,market_prices!$C:$C,C$1) -> 89.3229 | D6: =SUMIFS(market_prices!$E:$E,market_prices!$B:$B,$A6,market_prices!$C:$C,D$1) -> 80.7 | E6: =B6/B5-1 -> -0.00012215978 | F6: =rates[[#This Row],[EUR/INR]]/C5-1 -> -0.0014030435 | G6: =rates[[#This Row],[WTI Crude]]/D5-1 -> 0
A7: 45026 | B7: =SUMIFS(market_prices!$E:$E,market_prices!$B:$B,$A7,market_prices!$C:$C,B$1) -> 82.01 | C7: =SUMIFS(market_prices!$E:$E,market_prices!$B:$B,$A7,market_prices!$C:$C,C$1) -> 88.8988 | D7: =SUMIFS(market_prices!$E:$E,market_prices!$B:$B,$A7,market_prices!$C:$C,D$1) -> 79.79 | E7: =B7/B6-1 -> 0.0019547954 | F7: =rates[[#This Row],[EUR/INR]]/C6-1 -> -0.0047479426 | G7: =rates[[#This Row],[WTI Crude]]/D6-1 -> -0.011276332
A8: 45027 | B8: =SUMIFS(market_prices!$E:$E,market_prices!$B:$B,$A8,market_prices!$C:$C,B$1) -> 82.04 | C8: =SUMIFS(market_prices!$E:$E,market_prices!$B:$B,$A8,market_prices!$C:$C,C$1) -> 89.4728 | D8: =SUMIFS(market_prices!$E:$E,market_prices!$B:$B,$A8,market_prices!$C:$C,D$1) -> 81.54 | E8: =B8/B7-1 -> 0.00036580905 | F8: =rates[[#This Row],[EUR/INR]]/C7-1 -> 0.0064567801 | G8: =rates[[#This Row],[WTI Crude]]/D7-1 -> 0.021932573
A9: 45028 | B9: =SUMIFS(market_prices!$E:$E,market_prices!$B:$B,$A9,market_prices!$C:$C,B$1) -> 81.98 | C9: =SUMIFS(market_prices!$E:$E,market_prices!$B:$B,$A9,market_prices!$C:$C,C$1) -> 90.0714 | D9: =SUMIFS(market_prices!$E:$E,market_prices!$B:$B,$A9,market_prices!$C:$C,D$1) -> 83.26 | E9: =B9/B8-1 -> -0.00073135056 | F9: =rates[[#This Row],[EUR/INR]]/C8-1 -> 0.0066903014 | G9: =rates[[#This Row],[WTI Crude]]/D8-1 -> 0.021093942
A10: 45029 | B10: =SUMIFS(market_prices!$E:$E,market_prices!$B:$B,$A10,market_prices!$C:$C,B$1) -> 81.65 | C10: =SUMIFS(market_prices!$E:$E,market_prices!$B:$B,$A10,market_prices!$C:$C,C$1) -> 90.2559 | D10: =SUMIFS(market_prices!$E:$E,market_prices!$B:$B,$A10,market_prices!$C:$C,D$1) -> 82.16 | E10: =B10/B9-1 -> -0.004025372 | F10: =rates[[#This Row],[EUR/INR]]/C9-1 -> 0.002048375 | G10: =rates[[#This Row],[WTI Crude]]/D9-1 -> -0.013211626
A11: 45030 | B11: =SUMIFS(market_prices!$E:$E,market_prices!$B:$B,$A11,market_prices!$C:$C,B$1) -> 81.88 | C11: =SUMIFS(market_prices!$E:$E,market_prices!$B:$B,$A11,market_prices!$C:$C,C$1) -> 89.9042 | D11: =SUMIFS(market_prices!$E:$E,market_prices!$B:$B,$A11,market_prices!$C:$C,D$1) -> 82.58 | E11: =B11/B10-1 -> 0.0028169014 | F11: =rates[[#This Row],[EUR/INR]]/C10-1 -> -0.0038966982 | G11: =rates[[#This Row],[WTI Crude]]/D10-1 -> 0.0051119766
A12: 45033 | B12: =SUMIFS(market_prices!$E:$E,market_prices!$B:$B,$A12,market_prices!$C:$C,B$1) -> 81.98 | C12: =SUMIFS(market_prices!$E:$E,market_prices!$B:$B,$A12,market_prices!$C:$C,C$1) -> 89.4812 | D12: =SUMIFS(market_prices!$E:$E,market_prices!$B:$B,$A12,market_prices!$C:$C,D$1) -> 80.93 | E12: =B12/B11-1 -> 0.0012212995 | F12: =rates[[#This Row],[EUR/INR]]/C11-1 -> -0.0047050082 | G12: =rates[[#This Row],[WTI Crude]]/D11-1 -> -0.019980625
A13: 45034 | B13: =SUMIFS(market_prices!$E:$E,market_prices!$B:$B,$A13,market_prices!$C:$C,B$1) -> 82.08 | C13: =SUMIFS(market_prices!$E:$E,market_prices!$B:$B,$A13,market_prices!$C:$C,C$1) -> 89.9433 | D13: =SUMIFS(market_prices!$E:$E,market_prices!$B:$B,$A13,market_prices!$C:$C,D$1) -> 80.85 | E13: =B13/B12-1 -> 0.0012198097 | F13: =rates[[#This Row],[EUR/INR]]/C12-1 -> 0.0051642133 | G13: =rates[[#This Row],[WTI Crude]]/D12-1 -> -0.00098850859
A14: 45035 | B14: =SUMIFS(market_prices!$E:$E,market_prices!$B:$B,$A14,market_prices!$C:$C,B$1) -> 82.18 | C14: =SUMIFS(market_prices!$E:$E,market_prices!$B:$B,$A14,market_prices!$C:$C,C$1) -> 90.0118 | D14: =SUMIFS(market_prices!$E:$E,market_prices!$B:$B,$A14,market_prices!$C:$C,D$1) -> 79.18 | E14: =B14/B13-1 -> 0.0012183236 | F14: =rates[[#This Row],[EUR/INR]]/C13-1 -> 0.00076159091 | G14: =rates[[#This Row],[WTI Crude]]/D13-1 -> -0.020655535
... A522: 45747 | B522: =SUMIFS(market_prices!$E:$E,market_prices!$B:$B,$A522,market_prices!$C:$C,B$1) -> 85.43 | C522: =SUMIFS(market_prices!$E:$E,market_prices!$B:$B,$A522,market_prices!$C:$C,C$1) -> 92.2302 | D522: =SUMIFS(market_prices!$E:$E,market_prices!$B:$B,$A522,market_prices!$C:$C,D$1) -> 71.87 | E522: =B522/B521-1 -> -0.00093556309 | F522: =rates[[#This Row],[EUR/INR]]/C521-1 -> -0.0037040998 | G522: =rates[[#This Row],[WTI Crude]]/D521-1 -> 0.030542013

Sheet market_risk
B2: Metric | C2: USD/INR | D2: EUR/INR | E2: WTI Crude
B3: Daily volatility | C3: =_xlfn.STDEV.S('rates'!E3:E522) -> 0.0015458476 | D3: =_xlfn.STDEV.S('rates'!F3:F522) -> 0.0040790224 | E3: =_xlfn.STDEV.S('rates'!G3:G522) -> 0.018573567
B4: Annualised volatility | C4: =C3*SQRT(252) -> 0.024539569 | D4: =D3*SQRT(252) -> 0.064752473 | E4: =E3*SQRT(252) -> 0.29484623
B5: 1-day 95% VaR, worst fall | C5: =-_xlfn.PERCENTILE.INC('rates'!E3:E522,0.05) -> 0.0023700944 | D5: =-_xlfn.PERCENTILE.INC('rates'!F3:F522,0.05) -> 0.0059949849 | E5: =-_xlfn.PERCENTILE.INC('rates'!G3:G522,0.05) -> 0.031999705
B6: 1-day 95% VaR, worst rise | C6: =_xlfn.PERCENTILE.INC('rates'!E3:E522,0.95) -> 0.002319722 | D6: =_xlfn.PERCENTILE.INC('rates'!F3:F522,0.95) -> 0.0066767601 | E6: =_xlfn.PERCENTILE.INC('rates'!G3:G522,0.95) -> 0.029101812

Sheet working_capital
B2: Business Units | C2: Avg Receivables | D2: Revenue | E2: Avg inventory | F2: Purchases | G2: DSO | H2: DIO | I2: DPO | J2: CCC
B3: BU01 | C3: =AVERAGEIFS(treasury_monthly!$I:$I,treasury_monthly!$B:$B,$B3) -> 8.5298908e+08 | D3: =SUMIFS(invoices!$N:$N,invoices!$C:$C,$B3) -> 8.7421426e+09 | E3: =AVERAGEIFS(treasury_monthly!$H:$H,treasury_monthly!$B:$B,$B3) -> 2.6892938e+08 | F3: =SUMIFS(purchases!$M:$M,purchases!$C:$C,$B3) -> 3.019613e+09 | G3: =C3/D3*$C$8 -> 71.325194 | H3: =E3/F3*$C$8 -> 65.103499 | I3: =AVERAGEIFS(purchases!$N:$N,purchases!$C:$C,$B3) -> 44.481481 | J3: =G3+H3-I3 -> 91.947211
B4: BU02 | C4: =AVERAGEIFS(treasury_monthly!$I:$I,treasury_monthly!$B:$B,$B4) -> 5.1153696e+08 | D4: =SUMIFS(invoices!$N:$N,invoices!$C:$C,$B4) -> 4.6203727e+09 | E4: =AVERAGEIFS(treasury_monthly!$H:$H,treasury_monthly!$B:$B,$B4) -> 2.3320824e+08 | F4: =SUMIFS(purchases!$M:$M,purchases!$C:$C,$B4) -> 2.5845374e+09 | G4: =C4/D4*$C$8 -> 80.931463 | H4: =E4/F4*$C$8 -> 65.959665 | I4: =AVERAGEIFS(purchases!$N:$N,purchases!$C:$C,$B4) -> 45.079576 | J4: =G4+H4-I4 -> 101.81155
B5: BU03 | C5: =AVERAGEIFS(treasury_monthly!$I:$I,treasury_monthly!$B:$B,$B5) -> 3.2588516e+08 | D5: =SUMIFS(invoices!$N:$N,invoices!$C:$C,$B5) -> 3.1526427e+09 | E5: =AVERAGEIFS(treasury_monthly!$H:$H,treasury_monthly!$B:$B,$B5) -> 1.3118656e+08 | F5: =SUMIFS(purchases!$M:$M,purchases!$C:$C,$B5) -> 1.4889959e+09 | G5: =C5/D5*$C$8 -> 75.562656 | H5: =E5/F5*$C$8 -> 64.404054 | I5: =AVERAGEIFS(purchases!$N:$N,purchases!$C:$C,$B5) -> 44.475 | J5: =G5+H5-I5 -> 95.491709
B6: BU04 | C6: =AVERAGEIFS(treasury_monthly!$I:$I,treasury_monthly!$B:$B,$B6) -> 3.915878e+08 | D6: =SUMIFS(invoices!$N:$N,invoices!$C:$C,$B6) -> 4.3250676e+09 | E6: =AVERAGEIFS(treasury_monthly!$H:$H,treasury_monthly!$B:$B,$B6) -> 1.4440113e+08 | F6: =SUMIFS(purchases!$M:$M,purchases!$C:$C,$B6) -> 1.5354433e+09 | G6: =C6/D6*$C$8 -> 66.184094 | H6: =E6/F6*$C$8 -> 68.747071 | I6: =AVERAGEIFS(purchases!$N:$N,purchases!$C:$C,$B6) -> 43.392857 | J6: =G6+H6-I6 -> 91.538307
B7: BU05 | C7: =AVERAGEIFS(treasury_monthly!$I:$I,treasury_monthly!$B:$B,$B7) -> 3.4486197e+08 | D7: =SUMIFS(invoices!$N:$N,invoices!$C:$C,$B7) -> 2.9997631e+09 | E7: =AVERAGEIFS(treasury_monthly!$H:$H,treasury_monthly!$B:$B,$B7) -> 1.6941832e+08 | F7: =SUMIFS(purchases!$M:$M,purchases!$C:$C,$B7) -> 1.9365737e+09 | G7: =C7/D7*$C$8 -> 84.038003 | H7: =E7/F7*$C$8 -> 63.950468 | I7: =AVERAGEIFS(purchases!$N:$N,purchases!$C:$C,$B7) -> 44.532872 | J7: =G7+H7-I7 -> 103.4556
B8: Days in period | C8: =DATE(2025,3,31)-DATE(2023,4,1)+1 -> 731

Sheet aging_pivot
B2: Aging Group | C2: Count of invoice | D2: Open Balance in Cr.
B3: 1-30 | C3: 47 | D3: 33.451257
B4: 31-60 | C4: 15 | D4: 9.1154764
B5: 61-90 | C5: 11 | D5: 6.4302573
B6: 90+ | C6: 112 | D6: 43.607401
B7: Not yet due | C7: 231 | D7: 194.7867
B8: Grand Total | C8: 416 | D8: 287.39109
